Workbook

Sheet Dataset 1
B1: China Global Investment Tracker
B2: © Data compiled by The American Enterprise Institute and The Heritage Foundation. All rights reserved.
B4: Dataset 1 Investments
B6: Year | C6: Month | D6: Investor | E6: Quantity in Millions | F6: Share Size | G6: Transaction Party | H6: Sector | I6: Subsector | J6: Country | K6: Region | L6: BRI | M6: Greenfield
A7: =ROW()-6 -> 1 | B7: 2005 | C7: January | D7: Chinese Academy of Sciences | E7: 1740 | G7: IBM | H7: Technology | J7: USA | K7: USA
A8: =ROW()-6 -> 2 | B8: 2005 | C8: January | D8: Minmetals | E8: 500 | G8: Cubapetroleo | H8: Metals | J8: Cuba | K8: North America | M8: G
A9: =ROW()-6 -> 3 | B9: 2005 | C9: March | D9: MCC | E9: 670 | F9: 0.85 | G9: Highlands Pacific | H9: Metals | I9: Steel | J9: Papua New Guinea | K9: East Asia | M9: G
A10: =ROW()-6 -> 4 | B10: 2005 | C10: April | D10: China National Off-shore Oil (CNOOC) | E10: 130 | F10: 0.17 | G10: MEG Energy | H10: Energy | I10: Oil | J10: Canada | K10: North America
A11: =ROW()-6 -> 5 | B11: 2005 | C11: June | D11: China Petroleum and Chemical (Sinopec) | E11: 120 | F11: 0.4 | G11: Synenco | H11: Energy | I11: Oil | J11: Canada | K11: North America | M11: G
A12: =ROW()-6 -> 6 | B12: 2005 | C12: July | D12: Jiangsu Yuejin | E12: 100 | F12: 1 | G12: MG | H12: Transport | I12: Autos | J12: Britain | K12: Europe
A13: =ROW()-6 -> 7 | B13: 2005 | C13: July | D13: Sinohydro | E13: 280 | H13: Energy | I13: Hydro | J13: Cambodia | K13: East Asia | M13: G
A14: =ROW()-6 -> 8 | B14: 2005 | C14: August | D14: China National Petroleum Corp. (CNPC) | E14: 4200 | F14: 0.67 | G14: PetroKazakhstan | H14: Energy | I14: Oil | J14: Kazakhstan | K14: West Asia
A15: =ROW()-6 -> 9 | B15: 2005 | C15: September | D15: China National Petroleum Corp. (CNPC), China Petroleum and Chemical (Sinopec) | E15: 1420 | G15: EnCana | H15: Energy | I15: Oil | J15: Ecuador | K15: South America
A16: =ROW()-6 -> 10 | B16: 2005 | C16: September | D16: China Investment Corporation (CIC), Beijing Jingdeshun | E16: 200 | H16: Energy | I16: Oil | J16: Mongolia | K16: East Asia | M16: G
A17: =ROW()-6 -> 11 | B17: 2005 | C17: October | D17: Sinosteel | E17: 140 | F17: 0.5 | G17: Midwest | H17: Metals | I17: Steel | J17: Australia | K17: Australia | M17: G
A18: =ROW()-6 -> 12 | B18: 2005 | C18: October | D18: China National Chemical (ChemChina) | E18: 180 | F18: 1 | G18: Qenos | H18: Chemicals | J18: Australia | K18: Australia
A19: =ROW()-6 -> 13 | B19: 2005 | C19: December | D19: China National Petroleum Corp. (CNPC) | E19: 290 | F19: 0.16 | G19: Petro-Canada | H19: Energy | I19: Oil | J19: Syria | K19: Arab Middle East and North Africa
A20: =ROW()-6 -> 14 | B20: 2005 | C20: December | D20: Zhejiang Holley | E20: 150 | F20: 0.75 | G20: Amata | H20: Other | I20: Industry | J20: Thailand | K20: East Asia | M20: G
A21: =ROW()-6 -> 15 | B21: 2006 | C21: January | D21: China National Off-shore Oil (CNOOC) | E21: 2270 | F21: 0.45 | G21: South African Petroleum | H21: Energy | J21: Nigeria | K21: Sub-Saharan Africa
A22: =ROW()-6 -> 16 | B22: 2006 | C22: January | D22: China National Chemical (ChemChina) | E22: 480 | F22: 1 | G22: Adisseo | H22: Agriculture | J22: France | K22: Europe
A23: =ROW()-6 -> 17 | B23: 2006 | C23: January | D23: China National Petroleum Corp. (CNPC) | E23: 480 | F23: 1 | H23: Energy | I23: Oil | J23: Chad | K23: Sub-Saharan Africa
A24: =ROW()-6 -> 18 | B24: 2006 | C24: March | D24: China International Trust and Investment (CITIC) | E24: 2920 | G24: Mineralogy | H24: Metals | I24: Steel | J24: Australia | K24: Australia | M24: G
A25: =ROW()-6 -> 19 | B25: 2006 | C25: April | D25: Shanghai Municipal Government | E25: 1300 | F25: 1 | H25: Real estate | I25: Property | J25: Russian Federation | K25: West Asia | M25: G
A26: =ROW()-6 -> 20 | B26: 2006 | C26: May | D26: MCC | E26: 120 | F26: 1 | H26: Other | I26: Timber | J26: Russian Federation | K26: West Asia | M26: G
A27: =ROW()-6 -> 21 | B27: 2006 | C27: May | D27: China Petroleum and Chemical (Sinopec) | E27: 740 | F27: 0.75 | G27: Sonangol | H27: Energy | I27: Oil | J27: Angola | K27: Sub-Saharan Africa | M27: G
A28: =ROW()-6 -> 22 | B28: 2006 | C28: June | D28: China Petroleum and Chemical (Sinopec) | E28: 3490 | F28: 0.49 | G28: Rosneft | H28: Energy | J28: Russian Federation | K28: West Asia
A29: =ROW()-6 -> 23 | B29: 2006 | C29: July | D29: China International Trust and Investment (CITIC) | E29: 100 | F29: 0.51 | G29: Kuwait Petroleum | H29: Energy | I29: Oil | J29: Indonesia | K29: East Asia
A30: =ROW()-6 -> 24 | B30: 2006 | C30: July | D30: China National Petroleum Corp. (CNPC) | E30: 500 | G30: Rosneft | H30: Energy | J30: Russian Federation | K30: West Asia
A31: =ROW()-6 -> 25 | B31: 2006 | C31: August | D31: Wuxi Suntech | E31: 110 | F31: 0.67 | G31: MSK | H31: Energy | I31: Alternative | J31: Japan | K31: East Asia
A32: =ROW()-6 -> 26 | B32: 2006 | C32: September | D32: China Petroleum and Chemical (Sinopec) | E32: 430 | F32: 0.5 | G32: Omimex | H32: Energy | I32: Oil | J32: Colombia | K32: South America
A33: =ROW()-6 -> 27 | B33: 2006 | C33: October | D33: Jiangxi Copper | E33: 110 | F33: 0.75 | G33: bcMetals | H33: Metals | I33: Copper | J33: Canada | K33: North America | M33: G
A34: =ROW()-6 -> 28 | B34: 2006 | C34: October | D34: China International Trust and Investment (CITIC), Aluminum Corporation of China (Chinalco) | E34: 940 | H34: Metals | I34: Aluminum | J34: Egypt | K34: Arab Middle East and North Africa | M34: G
A35: =ROW()-6 -> 29 | B35: 2006 | C35: October | D35: China International Trust and Investment (CITIC) | E35: 1910 | G35: Nations Energy | H35: Energy | J35: Kazakhstan | K35: West Asia
A36: =ROW()-6 -> 30 | B36: 2006 | C36: November | D36: China Development Bank | E36: 800 | F36: 0.01 | G36: Anglo-American | H36: Metals | J36: Britain | K36: Europe
A37: =ROW()-6 -> 31 | B37: 2006 | C37: November | D37: Sinosteel | E37: 230 | F37: 0.5 | G37: Samancor Chrome | H37: Metals | I37: Steel | J37: South Africa | K37: Sub-Saharan Africa
A38: =ROW()-6 -> 32 | B38: 2006 | C38: November | D38: China Nonferrous | E38: 310 | F38: 1 | H38: Metals | I38: Copper | J38: Zambia | K38: Sub-Saharan Africa | M38: G
A39: =ROW()-6 -> 33 | B39: 2006 | C39: November | D39: Ex-Im Bank | E39: 1160 | H39: Metals | J39: Democratic Republic of the Congo | K39: Sub-Saharan Africa
A40: =ROW()-6 -> 34 | B40: 2006 | C40: November | D40: Three Gorges | E40: 140 | F40: 0.9 | G40: EDL | H40: Energy | I40: Hydro | J40: Laos | K40: East Asia | M40: G
A41: =ROW()-6 -> 35 | B41: 2006 | C41: December | D41: Bank of China | E41: 970 | F41: 1 | G41: WestLB, Singapore Air, local government | H41: Transport | I41: Aviation | J41: Singapore | K41: East Asia
A42: =ROW()-6 -> 36 | B42: 2006 | C42: December | D42: Sichuan Changhong | E42: 100 | F42: 0.75 | G42: Sterope investments | H42: Finance | I42: Investment | J42: Netherlands | K42: Europe
A43: =ROW()-6 -> 37 | B43: 2007 | C43: January | D43: China National Chemical (ChemChina) | E43: 700 | G43: Rhodia | H43: Chemicals | J43: France | K43: Europe
A44: =ROW()-6 -> 38 | B44: 2007 | C44: January | D44: China Mobile | E44: 280 | F44: 0.89 | G44: Millicom | H44: Technology | I44: Telecom | J44: Pakistan | K44: West Asia
A45: =ROW()-6 -> 39 | B45: 2007 | C45: January | D45: China National Petroleum Corp. (CNPC) | E45: 200 | F45: 0.5 | G45: EnCana | H45: Energy | I45: Oil | J45: Chad | K45: Sub-Saharan Africa
A46: =ROW()-6 -> 40 | B46: 2007 | C46: February | D46: Zijin Mining, China Nonferrous, Xiamen C&D | E46: 190 | F46: 45%, 35%, 20% | G46: Monterrico | H46: Metals | I46: Copper | J46: Peru | K46: South America
A47: =ROW()-6 -> 41 | B47: 2007 | C47: February | D47: China Petroleum and Chemical (Sinopec) | E47: 100 | G47: Syntroleum | H47: Energy | J47: USA | K47: USA
A48: =ROW()-6 -> 42 | B48: 2007 | C48: March | D48: Sinosteel | E48: 250 | H48: Metals | I48: Steel | J48: India | K48: West Asia | M48: G
A49: =ROW()-6 -> 43 | B49: 2007 | C49: May | D49: China Investment Corporation (CIC) | E49: 3030 | F49: 0.09 | G49: Blackstone | H49: Finance | I49: Investment | J49: USA | K49: USA
A50: =ROW()-6 -> 44 | B50: 2007 | C50: May | D50: LinkGlobal Logistics | E50: 130 | H50: Transport | I50: Aviation | J50: Germany | K50: Europe
A51: =ROW()-6 -> 45 | B51: 2007 | C51: May | D51: China Mobile | E51: 180 | F51: 0.11 | G51: Paktel | H51: Technology | I51: Telecom | J51: Pakistan | K51: West Asia
A52: =ROW()-6 -> 46 | B52: 2007 | C52: June | D52: Aluminum Corporation of China (Chinalco) | E52: 790 | F52: 1 | G52: Peru Copper | H52: Metals | I52: Copper | J52: Peru | K52: South America
A53: =ROW()-6 -> 47 | B53: 2007 | C53: June | D53: China Ocean Shipping (COSCO) | E53: 140 | F53: 0.8 | G53: Burg Industries | H53: Transport | I53: Shipping | J53: Netherlands | K53: Europe
A54: =ROW()-6 -> 48 | B54: 2007 | C54: June | D54: Sinohydro | E54: 200 | H54: Energy | I54: Hydro | J54: Laos | K54: East Asia | M54: G
A55: =ROW()-6 -> 49 | B55: 2007 | C55: July | D55: China International Trust and Investment (CITIC) | E55: 100 | F55: 0.08 | G55: Macarthur Coal | H55: Energy | I55: Coal | J55: Australia | K55: Australia
A56: =ROW()-6 -> 50 | B56: 2007 | C56: July | D56: China Development Bank | E56: 3040 | F56: 0.031 | G56: Barclays | H56: Finance | I56: Banking | J56: Britain | K56: Europe
A57: =ROW()-6 -> 51 | B57: 2007 | C57: July | D57: Golden Dragon | E57: 100 | F57: 1 | H57: Metals | I57: Copper | J57: Mexico | K57: North America | M57: G
A58: =ROW()-6 -> 52 | B58: 2007 | C58: July | D58: Datang | E58: 220 | H58: Energy | I58: Hydro | J58: Myanmar | K58: East Asia | M58: G
A59: =ROW()-6 -> 53 | B59: 2007 | C59: September | D59: Sany Heavy Industry | E59: 150 | H59: Real estate | I59: Construction | J59: USA | K59: USA | M59: G
A60: =ROW()-6 -> 54 | B60: 2007 | C60: September | D60: Ansteel | E60: 330 | F60: 0.5 | G60: Gindalbie Metals | H60: Metals | I60: Steel | J60: Australia | K60: Australia
A61: =ROW()-6 -> 55 | B61: 2007 | C61: October | D61: China Ocean Shipping (COSCO) | E61: 150 | F61: 0.2 | G61: Suez Container Terminal | H61: Logistics | J61: Egypt | K61: Arab Middle East and North Africa
A62: =ROW()-6 -> 56 | B62: 2007 | C62: October | D62: Industrial and Commercial Bank of China | E62: 5600 | F62: 0.2 | G62: Standard Bank | H62: Finance | I62: Banking | J62: South Africa | K62: Sub-Saharan Africa
A63: =ROW()-6 -> 57 | B63: 2007 | C63: October | D63: Southern Power Grid | E63: 170 | H63: Energy | I63: Hydro | J63: Laos | K63: East Asia | M63: G
A64: =ROW()-6 -> 58 | B64: 2007 | C64: November | D64: Ping An | E64: 2790 | F64: 0.042 | G64: Fortis | H64: Finance | J64: Belgium | K64: Europe
A65: =ROW()-6 -> 59 | B65: 2007 | C65: November | D65: Aluminum Corporation of China (Chinalco) | E65: 1200 | F65: 0.4 | G65: Binladin, MMC | H65: Metals | I65: Aluminum | J65: Saudi Arabia | K65: Arab Middle East and North Africa | M65: G
A66: =ROW()-6 -> 60 | B66: 2007 | C66: November | D66: MCC, Jiangxi Copper | E66: 2520 | H66: Metals | I66: Copper | J66: Afghanistan | K66: West Asia | M66: G
A67: =ROW()-6 -> 61 | B67: 2007 | C67: November | D67: Youngor | E67: 120 | F67: 1 | G67: Kellwood Co | H67: Other | I67: Textiles | J67: USA | K67: USA
A68: =ROW()-6 -> 62 | B68: 2007 | C68: December | D68: China Investment Corporation (CIC) | E68: 5000 | F68: 0.099 | G68: Morgan Stanley | H68: Finance | I68: Investment | J68: USA | K68: USA
A69: =ROW()-6 -> 63 | B69: 2007 | C69: December | D69: Minmetals, Jiangxi Copper | E69: 450 | F69: 1 | G69: Northern Peru Copper | H69: Metals | I69: Copper | J69: Peru | K69: South America
A70: =ROW()-6 -> 64 | B70: 2007 | C70: December | D70: Sinosteel | E70: 100 | F70: 0.67 | G70: Zimasco | H70: Metals | I70: Steel | J70: Zimbabwe | K70: Sub-Saharan Africa
A71: =ROW()-6 -> 65 | B71: 2007 | C71: December | D71: China Petroleum and Chemical (Sinopec) | E71: 2010 | F71: 0.51 | G71: National Iranian Oil | H71: Energy | I71: Oil | J71: Iran | K71: West Asia | M71: G
A72: =ROW()-6 -> 66 | B72: 2007 | C72: December | D72: Shenzhen Energy, China Development Bank | E72: 200 | H72: Energy | I72: Gas | J72: Ghana | K72: Sub-Saharan Africa | M72: G
A73: =ROW()-6 -> 67 | B73: 2008 | C73: January | D73: State Administration of Foreign Exchange (SAFE) | E73: 180 | F73: 1%, 1% | G73: Australia and New Zealand Banking, Commonwealth Bank of Australia, National Australia Bank | H73: Finance | I73: Banking | J73: Australia | K73: Australia
A74: =ROW()-6 -> 68 | B74: 2008 | C74: January | D74: WuXi Pharma | E74: 160 | F74: 1 | G74: AppTec Lab Services | H74: Health | J74: USA | K74: USA
A75: =ROW()-6 -> 69 | B75: 2008 | C75: January | D75: Jinchuan Group | E75: 210 | G75: Tyler Resources | H75: Metals | J75: Mexico | K75: North America
A76: =ROW()-6 -> 70 | B76: 2008 | C76: January | D76: State Grid | E76: 1580 | F76: 0.4 | G76: Monto Oro Grid | H76: Energy | J76: Philippines | K76: East Asia
A77: =ROW()-6 -> 71 | B77: 2008 | C77: February | D77: Minmetals, Xinxing Iron | E77: 1200 | F77: 20%, 35% | G77: Kelachandra and Manasara | H77: Metals | I77: Steel | J77: India | K77: West Asia | M77: G
A78: =ROW()-6 -> 72 | B78: 2008 | C78: February | D78: MCC | E78: 370 | F78: 1 | G78: Cape Lambert Iron | H78: Metals | I78: Steel | J78: Australia | K78: Australia | M78: G
A79: =ROW()-6 -> 73 | B79: 2008 | C79: February | D79: Sinochem | E79: 470 | F79: 0.168 | G79: Soco | H79: Energy | I79: Oil | J79: Yemen | K79: Arab Middle East and North Africa
A80: =ROW()-6 -> 74 | B80: 2008 | C80: February | D80: Aluminum Corporation of China (Chinalco) | E80: 12800 | F80: 0.11 | G80: Rio Tinto | H80: Metals | I80: Aluminum | J80: Australia | K80: Australia
A81: =ROW()-6 -> 75 | B81: 2008 | C81: March | D81: China Petroleum and Chemical (Sinopec) | E81: 560 | F81: 0.6 | G81: AED | H81: Energy | I81: Oil | J81: Australia | K81: Australia
A82: =ROW()-6 -> 76 | B82: 2008 | C82: March | D82: Huaneng Power | E82: 3040 | F82: 1 | G82: Temasek | H82: Utilities | J82: Singapore | K82: East Asia
A83: =ROW()-6 -> 77 | B83: 2008 | C83: March | D83: China Life | E83: 260 | F83: 0.01 | G83: Visa | H83: Finance | J83: USA | K83: USA
A84: =ROW()-6 -> 78 | B84: 2008 | C84: March | D84: China Investment Corporation (CIC) | E84: 100 | G84: Visa | H84: Finance | J84: USA | K84: USA
A85: =ROW()-6 -> 79 | B85: 2008 | C85: March | D85: Mindray Medical | E85: 200 | G85: Datascope | H85: Health | J85: USA | K85: USA
A86: =ROW()-6 -> 80 | B86: 2008 | C86: April | D86: China National Off-shore Oil (CNOOC) | E86: 130 | F86: 0.5 | G86: Husky Energy | H86: Energy | I86: Gas | J86: Indonesia | K86: East Asia | M86: G
A87: =ROW()-6 -> 81 | B87: 2008 | C87: April | D87: China Investment Corporation (CIC) | E87: 1400 | F87: 0.8 | G87: JC Flowers | H87: Finance | I87: Investment | J87: USA | K87: USA
A88: =ROW()-6 -> 82 | B88: 2008 | C88: April | D88: State Administration of Foreign Exchange (SAFE) | E88: 2800 | F88: 0.016 | G88: Total | H88: Energy | J88: France | K88: Europe
A89: =ROW()-6 -> 83 | B89: 2008 | C89: April | D89: State Administration of Foreign Exchange (SAFE) | E89: 2010 | F89: 0.01 | G89: BP | H89: Energy | J89: Britain | K89: Europe
A90: =ROW()-6 -> 84 | B90: 2008 | C90: April | D90: Hopu Investment | E90: 150 | G90: Lung Ming | H90: Metals | I90: Steel | J90: Mongolia | K90: East Asia
A91: =ROW()-6 -> 85 | B91: 2008 | C91: April | D91: State Administration of Foreign Exchange (SAFE) | E91: 1240 | F91: 0.01 | G91: Royal Dutch Shell | H91: Energy | J91: Netherlands | K91: Europe
A92: =ROW()-6 -> 86 | B92: 2008 | C92: May | D92: Aluminum Corporation of China (Chinalco) | E92: 2160 | F92: 1 | H92: Metals | I92: Copper | J92: Peru | K92: South America | M92: G
A93: =ROW()-6 -> 87 | B93: 2008 | C93: May | D93: China Investment Corporation (CIC) | E93: 110 | G93: OGX | H93: Energy | I93: Oil | J93: Brazil | K93: South America
A94: =ROW()-6 -> 88 | B94: 2008 | C94: June | D94: Zoomlion | E94: 250 | F94: 0.6 | G94: Compagnia Italiana Forme Acciaio | H94: Real estate | I94: Construction | J94: Italy | K94: Europe
A95: =ROW()-6 -> 89 | B95: 2008 | C95: June | D95: State Administration of Foreign Exchange (SAFE) | E95: 2510 | F95: 0.2 | G95: TPG | H95: Finance | I95: Investment | J95: USA | K95: USA
A96: =ROW()-6 -> 90 | B96: 2008 | C96: June | D96: China National Cereal, Oil and Foodstuffs (COFCO) | E96: 140 | F96: 0.05 | G96: Smithfield Foods | H96: Agriculture | J96: USA | K96: USA
A97: =ROW()-6 -> 91 | B97: 2008 | C97: June | D97: China National Nuclear | E97: 190 | H97: Metals | J97: Niger | K97: Sub-Saharan Africa | M97: G
A98: =ROW()-6 -> 92 | B98: 2008 | C98: June | D98: Huadian | E98: 580 | H98: Energy | I98: Hydro | J98: Cambodia | K98: East Asia | M98: G
A99: =ROW()-6 -> 93 | B99: 2008 | C99: July | D99: Sinochem | E99: 200 | F99: 0.51 | G99: GMG Global | H99: Agriculture | J99: Singapore | K99: East Asia
A100: =ROW()-6 -> 94 | B100: 2008 | C100: July | D100: China National Off-shore Oil (CNOOC) | E100: 2490 | F100: 1 | G100: Awilco Offshore | H100: Energy | I100: Oil | J100: Norway | K100: Europe
A101: =ROW()-6 -> 95 | B101: 2008 | C101: July | D101: China Nonferrous | E101: 810 | F101: 0.5 | G101: Tagaung Taung | H101: Metals | J101: Myanmar | K101: East Asia | M101: G
A102: =ROW()-6 -> 96 | B102: 2008 | C102: July | D102: Sinosteel | E102: 1320 | F102: 0.51 | G102: Midwest | H102: Metals | I102: Steel | J102: Australia | K102: Australia
...

Sheet Dataset 2
B1: China Global Investment Tracker
B2: © Data compiled by The American Enterprise Institute and The Heritage Foundation. All rights reserved.
B4: Dataset 2 Construction
B6: Year | C6: Month | D6: Contractor | E6: Quantity in Millions | F6: Share Size | G6: Transaction Party | H6: Sector | I6: Subsector | J6: Country | K6: Region | L6: BRI
A7: =ROW()-6 -> 1 | B7: 2005 | C7: January | D7: Sinohydro | E7: 100 | H7: Transport | I7: Aviation | J7: Qatar | K7: Arab Middle East and North Africa
A8: =ROW()-6 -> 2 | B8: 2005 | C8: February | D8: Sinohydro | E8: 150 | G8: Oman Wastewater Services | H8: Utilities | J8: Oman | K8: Arab Middle East and North Africa
A9: =ROW()-6 -> 3 | B9: 2005 | C9: February | D9: Sinohydro | E9: 370 | H9: Transport | I9: Autos | J9: Ecuador | K9: South America
A10: =ROW()-6 -> 4 | B10: 2005 | C10: March | D10: Sinoma | E10: 170 | G10: Riyadh Cement | H10: Real estate | I10: Construction | J10: Saudi Arabia | K10: Arab Middle East and North Africa
A11: =ROW()-6 -> 5 | B11: 2005 | C11: April | D11: China National Machinery Industry (Sinomach) | E11: 100 | H11: Utilities | J11: Sudan | K11: Arab Middle East and North Africa
A12: =ROW()-6 -> 6 | B12: 2005 | C12: April | D12: Minmetals, MCC | E12: 240 | H12: Metals | I12: Steel | J12: Brazil | K12: South America
A13: =ROW()-6 -> 7 | B13: 2005 | C13: May | D13: China National Petroleum Corp. (CNPC) | E13: 390 | G13: SONATRACH | H13: Energy | J13: Algeria | K13: Arab Middle East and North Africa
A14: =ROW()-6 -> 8 | B14: 2005 | C14: June | D14: China Railway Construction, China General Technology (Genertec) | E14: 1270 | G14: Cengiz and IC Ictas | H14: Transport | I14: Rail | J14: Turkey | K14: West Asia
A15: =ROW()-6 -> 9 | B15: 2005 | C15: June | D15: China National Machinery Industry (Sinomach), Sinohydro | E15: 860 | H15: Energy | I15: Coal | J15: Indonesia | K15: East Asia
A16: =ROW()-6 -> 10 | B16: 2005 | C16: June | D16: MCC | E16: 170 | H16: Transport | I16: Aviation | J16: Mauritania | K16: Arab Middle East and North Africa
A17: =ROW()-6 -> 11 | B17: 2005 | C17: July | D17: China International Trust and Investment (CITIC), Sinohydro | E17: 130 | H17: Energy | I17: Hydro | J17: Myanmar | K17: East Asia
A18: =ROW()-6 -> 12 | B18: 2005 | C18: September | D18: China Petroleum and Chemical (Sinopec) | E18: 350 | F18: 0.45 | G18: Aker Kvaerner | H18: Chemicals | J18: Saudi Arabia | K18: Arab Middle East and North Africa
A19: =ROW()-6 -> 13 | B19: 2005 | C19: October | D19: China Nonferrous | E19: 330 | G19: Kazakhstan Aluminum | H19: Metals | I19: Aluminum | J19: Kazakhstan | K19: West Asia
A20: =ROW()-6 -> 14 | B20: 2005 | C20: October | D20: China Communications Construction | E20: 200 | H20: Transport | I20: Autos | J20: Indonesia | K20: East Asia
A21: =ROW()-6 -> 15 | B21: 2005 | C21: November | D21: China North Industries (Norinco) | E21: 120 | G21: Electricite du Laos | H21: Energy | I21: Hydro | J21: Laos | K21: East Asia
A22: =ROW()-6 -> 16 | B22: 2005 | C22: November | D22: China International Trust and Investment (CITIC) | E22: 1190 | H22: Real estate | I22: Construction | J22: Venezuela | K22: South America
A23: =ROW()-6 -> 17 | B23: 2005 | C23: December | D23: China International Trust and Investment (CITIC), Aluminum Corporation of China (Chinalco) | E23: 900 | G23: South Iran Aluminum | H23: Metals | I23: Aluminum | J23: Iran | K23: West Asia
A24: =ROW()-6 -> 18 | B24: 2005 | C24: December | D24: Sinoma | E24: 580 | G24: Saudi Cement | H24: Real estate | I24: Construction | J24: Saudi Arabia | K24: Arab Middle East and North Africa
A25: =ROW()-6 -> 19 | B25: 2005 | C25: December | D25: China International Trust and Investment (CITIC) | E25: 430 | G25: Brazil Power | H25: Energy | I25: Coal | J25: Brazil | K25: South America
A26: =ROW()-6 -> 20 | B26: 2005 | C26: December | D26: Sinohydro | E26: 210 | H26: Agriculture | J26: Algeria | K26: Arab Middle East and North Africa
A27: =ROW()-6 -> 21 | B27: 2005 | C27: December | D27: China Communications Construction | E27: 210 | H27: Transport | I27: Autos | J27: Angola | K27: Sub-Saharan Africa
A28: =ROW()-6 -> 22 | B28: 2005 | C28: December | D28: China National Nuclear | E28: 860 | H28: Energy | J28: Pakistan | K28: West Asia
A29: =ROW()-6 -> 23 | B29: 2006 | C29: January | D29: State Construction Engineering | E29: 300 | G29: Dubai Properties | H29: Real estate | I29: Construction | J29: UAE | K29: Arab Middle East and North Africa
A30: =ROW()-6 -> 24 | B30: 2006 | C30: January | D30: China North Industries (Norinco) | E30: 310 | G30: Tehran Rail | H30: Transport | I30: Rail | J30: Iran | K30: West Asia
A31: =ROW()-6 -> 25 | B31: 2006 | C31: February | D31: Sinohydro | E31: 540 | H31: Real estate | I31: Construction | J31: Qatar | K31: Arab Middle East and North Africa
A32: =ROW()-6 -> 26 | B32: 2006 | C32: March | D32: China National Machinery Industry (Sinomach) | E32: 460 | H32: Energy | I32: Coal | J32: Sri Lanka | K32: West Asia
A33: =ROW()-6 -> 27 | B33: 2006 | C33: April | D33: China Petroleum and Chemical (Sinopec) | E33: 1290 | G33: Petrobras | H33: Energy | I33: Gas | J33: Brazil | K33: South America
A34: =ROW()-6 -> 28 | B34: 2006 | C34: May | D34: China International Trust and Investment (CITIC), China Railway Construction | E34: 6250 | H34: Transport | I34: Autos | J34: Algeria | K34: Arab Middle East and North Africa
A35: =ROW()-6 -> 29 | B35: 2006 | C35: May | D35: Shandong Electric Power Construction III | E35: 1500 | G35: Vedanta | H35: Energy | I35: Coal | J35: India | K35: West Asia
A36: =ROW()-6 -> 30 | B36: 2006 | C36: May | D36: China Power Engineering Consulting | E36: 110 | H36: Energy | J36: Nigeria | K36: Sub-Saharan Africa
A37: =ROW()-6 -> 31 | B37: 2006 | C37: June | D37: Tebian Electric Apparatus (TBEA) | E37: 400 | H37: Energy | J37: Tajikistan | K37: West Asia
A38: =ROW()-6 -> 32 | B38: 2006 | C38: June | D38: Weihai International Economic | E38: 160 | H38: Transport | I38: Aviation | J38: Congo | K38: Sub-Saharan Africa
A39: =ROW()-6 -> 33 | B39: 2006 | C39: June | D39: Sinoma | E39: 260 | G39: Arab Yemen Cement | H39: Real estate | I39: Construction | J39: Yemen | K39: Arab Middle East and North Africa
A40: =ROW()-6 -> 34 | B40: 2006 | C40: June | D40: Jiangsu International Cooperation Corp | E40: 170 | H40: Utilities | J40: Botswana | K40: Sub-Saharan Africa
A41: =ROW()-6 -> 35 | B41: 2006 | C41: July | D41: China Communications Construction | E41: 300 | H41: Transport | I41: Autos | J41: Tajikistan | K41: West Asia
A42: =ROW()-6 -> 36 | B42: 2006 | C42: July | D42: State Construction Engineering | E42: 260 | H42: Transport | I42: Aviation | J42: Algeria | K42: Arab Middle East and North Africa
A43: =ROW()-6 -> 37 | B43: 2006 | C43: July | D43: China Petroleum and Chemical (Sinopec) | E43: 2840 | H43: Energy | I43: Oil | J43: Iran | K43: West Asia
A44: =ROW()-6 -> 38 | B44: 2006 | C44: July | D44: Dongfang Electric | E44: 330 | F44: 0.55 | G44: Marubeni | H44: Energy | I44: Coal | J44: Vietnam | K44: East Asia
A45: =ROW()-6 -> 39 | B45: 2006 | C45: September | D45: ZTE (Zhongxing Telecommunications Equipment), Huawei, China Communications Construction | E45: 2400 | G45: Ethiopia Telecom | H45: Technology | I45: Telecom | J45: Ethiopia | K45: Sub-Saharan Africa
A46: =ROW()-6 -> 40 | B46: 2006 | C46: September | D46: Huawei | E46: 550 | G46: Ufone | H46: Technology | I46: Telecom | J46: Pakistan | K46: West Asia
A47: =ROW()-6 -> 41 | B47: 2006 | C47: November | D47: China International Trust and Investment (CITIC) | E47: 340 | G47: ThyssenKrupp | H47: Metals | I47: Steel | J47: Brazil | K47: South America
A48: =ROW()-6 -> 42 | B48: 2006 | C48: November | D48: China Communications Construction | E48: 490 | H48: Transport | I48: Autos | J48: Pakistan | K48: West Asia
A49: =ROW()-6 -> 43 | B49: 2006 | C49: November | D49: China General Technology (Genertec) | E49: 220 | H49: Real estate | I49: Construction | J49: Yemen | K49: Arab Middle East and North Africa
A50: =ROW()-6 -> 44 | B50: 2006 | C50: November | D50: China National Chemical Engineering | E50: 180 | G50: Bosowa | H50: Energy | I50: Coal | J50: Indonesia | K50: East Asia
A51: =ROW()-6 -> 45 | B51: 2006 | C51: November | D51: China National Petroleum Corp. (CNPC) | E51: 430 | H51: Agriculture | J51: Vietnam | K51: East Asia
A52: =ROW()-6 -> 46 | B52: 2006 | C52: December | D52: Sinohydro | E52: 130 | H52: Transport | I52: Autos | J52: Ethiopia | K52: Sub-Saharan Africa
A53: =ROW()-6 -> 47 | B53: 2006 | C53: December | D53: Harbin Electric | E53: 520 | H53: Energy | I53: Coal | J53: Indonesia | K53: East Asia
A54: =ROW()-6 -> 48 | B54: 2006 | C54: December | D54: Huadian | E54: 250 | H54: Energy | I54: Hydro | J54: Indonesia | K54: East Asia
A55: =ROW()-6 -> 49 | B55: 2006 | C55: December | D55: Shanghai Electric | E55: 260 | G55: Truba Alam Manunggal | H55: Energy | I55: Coal | J55: Indonesia | K55: East Asia
A56: =ROW()-6 -> 50 | B56: 2006 | C56: December | D56: Sinoma | E56: 130 | G56: Mugher Cement | H56: Real estate | I56: Construction | J56: Ethiopia | K56: Sub-Saharan Africa
A57: =ROW()-6 -> 51 | B57: 2007 | C57: January | D57: State Construction Engineering | E57: 350 | H57: Real estate | I57: Construction | J57: UAE | K57: Arab Middle East and North Africa
A58: =ROW()-6 -> 52 | B58: 2007 | C58: January | D58: Shandong Electric Power Construction | E58: 3990 | H58: Energy | I58: Coal | J58: India | K58: West Asia
A59: =ROW()-6 -> 53 | B59: 2007 | C59: January | D59: State Construction Engineering | E59: 160 | H59: Transport | I59: Autos | J59: UAE | K59: Arab Middle East and North Africa
A60: =ROW()-6 -> 54 | B60: 2007 | C60: January | D60: MCC | E60: 1110 | G60: CITIC | H60: Metals | I60: Steel | J60: Australia | K60: Australia
A61: =ROW()-6 -> 55 | B61: 2007 | C61: January | D61: Aluminum Corporation of China (Chinalco) | E61: 100 | G61: Vedanta | H61: Metals | I61: Aluminum | J61: India | K61: West Asia
A62: =ROW()-6 -> 56 | B62: 2007 | C62: January | D62: China Railway Construction | E62: 1830 | H62: Transport | I62: Rail | J62: Angola | K62: Sub-Saharan Africa
A63: =ROW()-6 -> 57 | B63: 2007 | C63: February | D63: Gezhouba | E63: 180 | H63: Transport | I63: Autos | J63: India | K63: West Asia
A64: =ROW()-6 -> 58 | B64: 2007 | C64: February | D64: Shanghai Shengong, Shanghai Foreign Economic and Technological Cooperation | E64: 100 | H64: Utilities | J64: Pakistan | K64: West Asia
A65: =ROW()-6 -> 59 | B65: 2007 | C65: March | D65: China General Technology (Genertec) | E65: 430 | H65: Energy | I65: Coal | J65: Indonesia | K65: East Asia
A66: =ROW()-6 -> 60 | B66: 2007 | C66: March | D66: Sinohydro, China Communications Construction | E66: 360 | H66: Transport | I66: Shipping | J66: Sri Lanka | K66: West Asia
A67: =ROW()-6 -> 61 | B67: 2007 | C67: March | D67: State Construction Engineering | E67: 430 | H67: Finance | J67: Kuwait | K67: Arab Middle East and North Africa
A68: =ROW()-6 -> 62 | B68: 2007 | C68: March | D68: China National Chemical Engineering | E68: 540 | G68: PLN | H68: Energy | I68: Coal | J68: Indonesia | K68: East Asia
A69: =ROW()-6 -> 63 | B69: 2007 | C69: March | D69: China National Machinery Industry (Sinomach) | E69: 110 | H69: Agriculture | J69: Venezuela | K69: South America
A70: =ROW()-6 -> 64 | B70: 2007 | C70: March | D70: Sinoma | E70: 690 | G70: Dangote | H70: Real estate | I70: Construction | J70: Nigeria | K70: Sub-Saharan Africa
A71: =ROW()-6 -> 65 | B71: 2007 | C71: April | D71: China National Machinery Industry (Sinomach), Sinohydro | E71: 650 | H71: Energy | I71: Hydro | J71: Equatorial Guinea | K71: Sub-Saharan Africa
A72: =ROW()-6 -> 66 | B72: 2007 | C72: April | D72: China National Machinery Industry (Sinomach), China Nonferrous | E72: 990 | G72: Western Way | H72: Metals | I72: Aluminum | J72: Saudi Arabia | K72: Arab Middle East and North Africa
A73: =ROW()-6 -> 67 | B73: 2007 | C73: April | D73: Sinohydro | E73: 600 | H73: Energy | I73: Hydro | J73: Ghana | K73: Sub-Saharan Africa
A74: =ROW()-6 -> 68 | B74: 2007 | C74: May | D74: China National Machinery Industry (Sinomach) | E74: 150 | H74: Energy | J74: Pakistan | K74: West Asia
A75: =ROW()-6 -> 69 | B75: 2007 | C75: May | D75: China National Petroleum Corp. (CNPC) | E75: 150 | H75: Energy | I75: Gas | J75: Turkmenistan | K75: West Asia
A76: =ROW()-6 -> 70 | B76: 2007 | C76: May | D76: China National Building Material | E76: 250 | G76: Al Essayi | H76: Real estate | I76: Construction | J76: Yemen | K76: Arab Middle East and North Africa
A77: =ROW()-6 -> 71 | B77: 2007 | C77: June | D77: China Communications Construction | E77: 410 | H77: Transport | I77: Shipping | J77: Kuwait | K77: Arab Middle East and North Africa
A78: =ROW()-6 -> 72 | B78: 2007 | C78: June | D78: China National Petroleum Corp. (CNPC) | E78: 560 | H78: Energy | I78: Gas | J78: India | K78: West Asia
A79: =ROW()-6 -> 73 | B79: 2007 | C79: July | D79: China International Trust and Investment (CITIC) | E79: 110 | H79: Agriculture | J79: Uzbekistan | K79: West Asia
A80: =ROW()-6 -> 74 | B80: 2007 | C80: August | D80: Dongfang Electric, Shanghai Electric | E80: 1270 | G80: PLN | H80: Energy | I80: Coal | J80: Indonesia | K80: East Asia
A81: =ROW()-6 -> 75 | B81: 2007 | C81: August | D81: MCC | E81: 640 | G81: CITIC | H81: Metals | I81: Steel | J81: Australia | K81: Australia
A82: =ROW()-6 -> 76 | B82: 2007 | C82: September | D82: Three Gorges | E82: 150 | H82: Transport | I82: Autos | J82: Ethiopia | K82: Sub-Saharan Africa
A83: =ROW()-6 -> 77 | B83: 2007 | C83: September | D83: Huawei | E83: 150 | G83: Bharti Airtel | H83: Technology | I83: Telecom | J83: Sri Lanka | K83: West Asia
A84: =ROW()-6 -> 78 | B84: 2007 | C84: September | D84: China National Machinery Industry (Sinomach) | E84: 210 | H84: Energy | I84: Gas | J84: Azerbaijan | K84: West Asia
A85: =ROW()-6 -> 79 | B85: 2007 | C85: October | D85: Sinoma | E85: 170 | G85: Holcim | H85: Real estate | I85: Construction | J85: Hungary | K85: Europe
A86: =ROW()-6 -> 80 | B86: 2007 | C86: October | D86: Gezhouba | E86: 210 | F86: 0.49 | G86: Iran Water and Power | H86: Energy | I86: Hydro | J86: Iran | K86: West Asia
A87: =ROW()-6 -> 81 | B87: 2007 | C87: October | D87: China Nonferrous | E87: 110 | F87: 0.2 | G87: Jahad Tahghighat | H87: Metals | I87: Aluminum | J87: Iran | K87: West Asia
A88: =ROW()-6 -> 82 | B88: 2007 | C88: October | D88: China National Machinery Industry (Sinomach) | E88: 160 | G88: Tanzanian Power | H88: Agriculture | J88: Tanzania | K88: Sub-Saharan Africa
A89: =ROW()-6 -> 83 | B89: 2007 | C89: October | D89: China Electronics Corporation | E89: 100 | F89: 0.5 | G89: Pakistan Infrastructure | H89: Transport | I89: Rail | J89: Jordan | K89: Arab Middle East and North Africa
A90: =ROW()-6 -> 84 | B90: 2007 | C90: October | D90: China National Machinery Industry (Sinomach) | E90: 610 | G90: Eren Power | H90: Energy | I90: Coal | J90: Turkey | K90: West Asia
A91: =ROW()-6 -> 85 | B91: 2007 | C91: November | D91: Guizhou Hongfu | E91: 350 | H91: Chemicals | J91: Saudi Arabia | K91: Arab Middle East and North Africa
A92: =ROW()-6 -> 86 | B92: 2007 | C92: November | D92: China Communications Construction | E92: 230 | H92: Logistics | J92: Saudi Arabia | K92: Arab Middle East and North Africa
A93: =ROW()-6 -> 87 | B93: 2007 | C93: December | D93: China International Trust and Investment (CITIC) | E93: 620 | H93: Real estate | I93: Construction | J93: Belarus | K93: Europe
A94: =ROW()-6 -> 88 | B94: 2007 | C94: December | D94: Shanghai Electric | E94: 1080 | H94: Energy | J94: Iraq | K94: Arab Middle East and North Africa
A95: =ROW()-6 -> 89 | B95: 2007 | C95: December | D95: China National Petroleum Corp. (CNPC) | E95: 880 | H95: Energy | I95: Gas | J95: Uzbekistan | K95: West Asia
A96: =ROW()-6 -> 90 | B96: 2007 | C96: December | D96: China National Petroleum Corp. (CNPC) | E96: 1310 | H96: Energy | I96: Gas | J96: Kazakhstan | K96: West Asia
A97: =ROW()-6 -> 91 | B97: 2007 | C97: December | D97: Sinohydro | E97: 120 | H97: Entertainment | J97: Angola | K97: Sub-Saharan Africa
A98: =ROW()-6 -> 92 | B98: 2007 | C98: December | D98: Sinohydro | E98: 160 | G98: SOMINA | H98: Metals | J98: Niger | K98: Sub-Saharan Africa
A99: =ROW()-6 -> 93 | B99: 2007 | C99: December | D99: Sinohydro | E99: 140 | H99: Tourism | J99: UAE | K99: Arab Middle East and North Africa
A100: =ROW()-6 -> 94 | B100: 2008 | C100: January | D100: China Communications Construction | E100: 160 | G100: Saigon International Terminals | H100: Transport | I100: Shipping | J100: Vietnam | K100: East Asia
A101: =ROW()-6 -> 95 | B101: 2008 | C101: January | D101: MCC | E101: 200 | G101: Loyal Capital | H101: Tourism | J101: Georgia | K101: West Asia
A102: =ROW()-6 -> 96 | B102: 2008 | C102: January | D102: China Communications Construction | E102: 290 | H102: Transport | I102: Shipping | J102: Mauritania | K102: Arab Middle East and North Africa
...

Sheet Dataset 3
B1: China Global Investment Tracker
B2: © Data compiled by The American Enterprise Institute and The Heritage Foundation. All rights reserved.
B4: Dataset 3 Troubled Transactions
B6: Year | C6: Month | D6: Chinese Entity | E6: Quantity in Millions | F6: Transaction Party | G6: Sector | H6: Subsector | I6: Country | J6: Region | K6: Greenfield | L6: BRI
A7: =ROW()-6 -> 1 | B7: 2005 | C7: July | D7: China National Off-shore Oil (CNOOC) | E7: 18000 | F7: Unocal | G7: Energy | I7: USA | J7: USA
A8: =ROW()-6 -> 2 | B8: 2006 | C8: July | D8: China Mobile | E8: 5300 | F8: Millicom | G8: Technology | H8: Telecom | I8: Luxembourg | J8: Europe
A9: =ROW()-6 -> 3 | B9: 2006 | C9: July | D9: China National Petroleum Corp. (CNPC) | E9: 2500 | F9: Rosneft | G9: Energy | H9: Gas | I9: Russian Federation | J9: West Asia
A10: =ROW()-6 -> 4 | B10: 2006 | C10: July | D10: China National Petroleum Corp. (CNPC) | E10: 1390 | F10: KazMunaiGaz | G10: Energy | H10: Gas | I10: Kazakhstan | J10: West Asia
A11: =ROW()-6 -> 5 | B11: 2006 | C11: July | D11: China Ocean Shipping (COSCO) | E11: 140 | F11: Burg | G11: Transport | H11: Shipping | I11: Netherlands | J11: Europe
A12: =ROW()-6 -> 6 | B12: 2006 | C12: September | D12: China National Off-shore Oil (CNOOC) | E12: 16000 | G12: Energy | H12: Gas | I12: Iran | J12: West Asia | K12: G
A13: =ROW()-6 -> 7 | B13: 2006 | C13: October | D13: Southern Power Grid | E13: 190 | G13: Energy | H13: Hydro | I13: Cambodia | J13: East Asia
A14: =ROW()-6 -> 8 | B14: 2006 | C14: November | D14: China Railway Construction | E14: 7450 | G14: Transport | H14: Rail | I14: Nigeria | J14: Sub-Saharan Africa
A15: =ROW()-6 -> 9 | B15: 2006 | C15: November | D15: Aluminum Corporation of China (Chinalco) | E15: 790 | F15: Vietnam National Coal-Mineral Industries | G15: Metals | H15: Aluminum | I15: Vietnam | J15: East Asia | K15: G
A16: =ROW()-6 -> 10 | B16: 2006 | C16: December | D16: Jinchuan Group | E16: 1000 | F16: Philnico | G16: Metals | H16: Steel | I16: Philippines | J16: East Asia | K16: G
A17: =ROW()-6 -> 11 | B17: 2007 | C17: January | D17: Minmetals | E17: 500 | G17: Metals | I17: Cuba | J17: North America
A18: =ROW()-6 -> 12 | B18: 2007 | C18: March | D18: China Petroleum and Chemical (Sinopec) | E18: 3400 | F18: Sonangol | G18: Energy | H18: Oil | I18: Angola | J18: Sub-Saharan Africa | K18: G
A19: =ROW()-6 -> 13 | B19: 2007 | C19: April | D19: China Petroleum and Chemical (Sinopec) | E19: 110 | F19: Uzbekneftegas | G19: Energy | H19: Oil | I19: Uzbekistan | J19: West Asia
A20: =ROW()-6 -> 14 | B20: 2007 | C20: April | D20: Gezhouba | E20: 1440 | G20: Energy | H20: Hydro | I20: Nigeria | J20: Sub-Saharan Africa
A21: =ROW()-6 -> 15 | B21: 2007 | C21: April | D21: China Merchants | E21: 1000 | G21: Logistics | I21: Vietnam | J21: East Asia
A22: =ROW()-6 -> 16 | B22: 2007 | C22: May | D22: TCL | E22: 300 | F22: Thomson | G22: Technology | I22: France | J22: Europe
A23: =ROW()-6 -> 17 | B23: 2007 | C23: June | D23: China National Off-shore Oil (CNOOC) | E23: 370 | F23: Talisman Energy | G23: Energy | H23: Gas | I23: Indonesia | J23: East Asia
A24: =ROW()-6 -> 18 | B24: 2007 | C24: September | D24: China Development Bank, Jilin Fuhua Agricultural Science and Technology Development | E24: 4130 | G24: Agriculture | I24: Philippines | J24: East Asia | K24: G
A25: =ROW()-6 -> 19 | B25: 2007 | C25: September | D25: Tianye Auto, Chamco | E25: 300 | G25: Transport | H25: Autos | I25: Mexico | J25: North America | K25: G
A26: =ROW()-6 -> 20 | B26: 2007 | C26: October | D26: China Development Bank | E26: 980 | F26: Barclays | G26: Finance | H26: Banking | I26: Britain | J26: Europe
A27: =ROW()-6 -> 21 | B27: 2007 | C27: November | D27: Perfect Field | E27: 1750 | F27: Rowsley | G27: Energy | H27: Alternative | I27: Singapore | J27: East Asia
A28: =ROW()-6 -> 22 | B28: 2007 | C28: November | D28: MCC, Jiangxi Copper | E28: 2520 | G28: Metals | H28: Copper | I28: Afghanistan | J28: West Asia | K28: G
A29: =ROW()-6 -> 23 | B29: 2007 | C29: December | D29: China National Chemical (ChemChina) | E29: 1310 | F29: Nufarm | G29: Agriculture | I29: Australia | J29: Australia
A30: =ROW()-6 -> 24 | B30: 2008 | C30: January | D30: China Development Bank | E30: 2000 | F30: Citigroup | G30: Finance | H30: Banking | I30: USA | J30: USA
A31: =ROW()-6 -> 25 | B31: 2008 | C31: February | D31: ZTE (Zhongxing Telecommunications Equipment) | E31: 300 | G31: Technology | H31: Telecom | I31: Philippines | J31: East Asia
A32: =ROW()-6 -> 26 | B32: 2008 | C32: March | D32: Huawei | E32: 600 | F32: 3Com | G32: Technology | H32: Telecom | I32: USA | J32: USA
A33: =ROW()-6 -> 27 | B33: 2008 | C33: March | D33: China International Trust and Investment (CITIC) | E33: 1000 | F33: Bear Stearns | G33: Finance | H33: Investment | I33: USA | J33: USA
A34: =ROW()-6 -> 28 | B34: 2008 | C34: April | D34: Great Wall Technology | E34: 300 | F34: Iomega | G34: Technology | I34: USA | J34: USA
A35: =ROW()-6 -> 29 | B35: 2008 | C35: April | D35: Shougang Group | E35: 360 | F35: Mt. Gibson | G35: Metals | H35: Steel | I35: Australia | J35: Australia
A36: =ROW()-6 -> 30 | B36: 2008 | C36: September | D36: State Administration of Foreign Exchange (SAFE) | E36: 100 | F36: TPG | G36: Finance | H36: Banking | I36: USA | J36: USA
A37: =ROW()-6 -> 31 | B37: 2008 | C37: September | D37: China Development Bank | E37: 13900 | F37: Dresdner Bank | G37: Finance | H37: Banking | I37: Germany | J37: Europe
A38: =ROW()-6 -> 32 | B38: 2008 | C38: September | D38: Minmetals | E38: 1450 | F38: Codelco | G38: Metals | H38: Copper | I38: Chile | J38: South America
A39: =ROW()-6 -> 33 | B39: 2008 | C39: September | D39: Ping An | E39: 3000 | F39: Fortis | G39: Finance | I39: Belgium | J39: Europe
A40: =ROW()-6 -> 34 | B40: 2008 | C40: September | D40: Shandong Energy | E40: 1210 | F40: Linc Energy | G40: Energy | H40: Coal | I40: Australia | J40: Australia | K40: G
A41: =ROW()-6 -> 35 | B41: 2008 | C41: November | D41: Ping An | E41: 2360 | F41: Fortis | G41: Finance | H41: Insurance | I41: Belgium | J41: Europe
A42: =ROW()-6 -> 36 | B42: 2008 | C42: December | D42: Sinoma | E42: 2570 | F42: Dangote | G42: Real estate | H42: Construction | I42: Nigeria | J42: Sub-Saharan Africa
A43: =ROW()-6 -> 37 | B43: 2009 | C43: January | D43: Zijin Mining | E43: 1400 | G43: Metals | H43: Copper | I43: Peru | J43: South America | K43: G
A44: =ROW()-6 -> 38 | B44: 2009 | C44: January | D44: BaoWu Steel (Baosteel) | E44: 2880 | F44: CVRD | G44: Metals | H44: Steel | I44: Brazil | J44: South America | K44: G
A45: =ROW()-6 -> 39 | B45: 2009 | C45: January | D45: SAIC Motor (Shanghai Auto) | E45: 520 | G45: Transport | H45: Autos | I45: South Korea | J45: East Asia
A46: =ROW()-6 -> 40 | B46: 2009 | C46: February | D46: Minmetals | E46: 350 | F46: Oz Minerals | G46: Metals | I46: Australia | J46: Australia
A47: =ROW()-6 -> 41 | B47: 2009 | C47: March | D47: Dongfang Electric | E47: 520 | G47: Energy | H47: Gas | I47: Pakistan | J47: West Asia
A48: =ROW()-6 -> 42 | B48: 2009 | C48: March | D48: Property consortium | E48: 520 | F48: Pacific Holdings | G48: Real estate | H48: Property | I48: Japan | J48: East Asia
A49: =ROW()-6 -> 43 | B49: 2009 | C49: April | D49: Bright Foods | E49: 1480 | F49: CSR | G49: Agriculture | I49: Australia | J49: Australia
A50: =ROW()-6 -> 44 | B50: 2009 | C50: April | D50: Sinosteel | E50: 1500 | G50: Metals | H50: Steel | I50: India | J50: West Asia
A51: =ROW()-6 -> 45 | B51: 2009 | C51: June | D51: Aluminum Corporation of China (Chinalco) | E51: 19500 | F51: Rio Tinto | G51: Metals | H51: Aluminum | I51: Australia | J51: Australia
A52: =ROW()-6 -> 46 | B52: 2009 | C52: August | D52: Ex-Im Bank | E52: 3000 | G52: Metals | I52: Democratic Republic of the Congo | J52: Sub-Saharan Africa
A53: =ROW()-6 -> 47 | B53: 2009 | C53: September | D53: China National Petroleum Corp. (CNPC) | E53: 460 | F53: Verenex Energy | G53: Energy | H53: Oil | I53: Libya | J53: Arab Middle East and North Africa
A54: =ROW()-6 -> 48 | B54: 2009 | C54: September | D54: China Petroleum and Chemical (Sinopec), China National Petroleum Corp. (CNPC) | E54: 1300 | F54: Marathon | G54: Energy | H54: Oil | I54: Angola | J54: Sub-Saharan Africa
A55: =ROW()-6 -> 49 | B55: 2009 | C55: September | D55: China Nonferrous | E55: 220 | F55: Lynas | G55: Metals | I55: Australia | J55: Australia
A56: =ROW()-6 -> 50 | B56: 2009 | C56: October | D56: State Construction Engineering | E56: 180 | G56: Transport | H56: Aviation | I56: Qatar | J56: Arab Middle East and North Africa
A57: =ROW()-6 -> 51 | B57: 2009 | C57: November | D57: Minsheng Bank | E57: 120 | F57: UCB | G57: Finance | H57: Banking | I57: USA | J57: USA
A58: =ROW()-6 -> 52 | B58: 2009 | C58: November | D58: A-Power | E58: 900 | F58: Renewable Energy Group | G58: Energy | H58: Alternative | I58: USA | J58: USA | K58: G
A59: =ROW()-6 -> 53 | B59: 2009 | C59: December | D59: China International Trust and Investment (CITIC) | E59: 140 | F59: ThyssenKrupp | G59: Metals | H59: Steel | I59: Brazil | J59: South America
A60: =ROW()-6 -> 54 | B60: 2009 | C60: December | D60: Zhejiang Construction Investment | E60: 330 | G60: Entertainment | I60: Algeria | J60: Arab Middle East and North Africa
A61: =ROW()-6 -> 55 | B61: 2010 | C61: January | D61: State Development and Investment Corp. | E61: 1200 | F61: MagIndustries | G61: Agriculture | I61: Congo | J61: Sub-Saharan Africa
A62: =ROW()-6 -> 56 | B62: 2010 | C62: February | D62: Sichuan Tengzhong | E62: 150 | F62: Hummer | G62: Transport | H62: Autos | I62: USA | J62: USA
A63: =ROW()-6 -> 57 | B63: 2010 | C63: March | D63: Tonghua Iron and Steel | E63: 870 | G63: Metals | H63: Steel | I63: North Korea | J63: East Asia
A64: =ROW()-6 -> 58 | B64: 2010 | C64: May | D64: Haier | E64: 910 | G64: Other | H64: Consumer | I64: Venezuela | J64: South America | K64: G
A65: =ROW()-6 -> 59 | B65: 2010 | C65: May | D65: China Investment Corporation (CIC) | E65: 550 | F65: Penn West | G65: Energy | H65: Oil | I65: Canada | J65: North America
A66: =ROW()-6 -> 60 | B66: 2010 | C66: June | D66: State Grid | E66: 1200 | F66: Quadra Mining | G66: Metals | H66: Copper | I66: Chile | J66: South America | K66: G
A67: =ROW()-6 -> 61 | B67: 2010 | C67: July | D67: Aluminum Corporation of China (Chinalco) | E67: 1350 | F67: Rio Tinto | G67: Metals | H67: Steel | I67: Guinea | J67: Sub-Saharan Africa | K67: G
A68: =ROW()-6 -> 62 | B68: 2010 | C68: July | D68: Zijin Mining | E68: 500 | F68: Indophil Resoures | G68: Metals | I68: Philippines | J68: East Asia
A69: =ROW()-6 -> 63 | B69: 2010 | C69: July | D69: Huawei | E69: 480 | F69: 2Wire | G69: Technology | H69: Telecom | I69: USA | J69: USA
A70: =ROW()-6 -> 64 | B70: 2010 | C70: July | D70: Aluminum Corporation of China (Chinalco) | E70: 2200 | G70: Metals | H70: Aluminum | I70: Australia | J70: Australia
A71: =ROW()-6 -> 65 | B71: 2010 | C71: August | D71: China Railway Construction | E71: 790 | G71: Transport | H71: Rail | I71: Angola | J71: Sub-Saharan Africa
A72: =ROW()-6 -> 66 | B72: 2010 | C72: August | D72: Huawei | E72: 1300 | F72: Motorola | G72: Technology | H72: Telecom | I72: USA | J72: USA
A73: =ROW()-6 -> 67 | B73: 2010 | C73: September | D73: MCC | E73: 370 | F73: Cape Lambert | G73: Metals | H73: Steel | I73: Australia | J73: Australia
A74: =ROW()-6 -> 68 | B74: 2010 | C74: September | D74: China Investment Corporation (CIC) | E74: 360 | F74: PT Bumi Resources | G74: Metals | I74: Indonesia | J74: East Asia
A75: =ROW()-6 -> 69 | B75: 2010 | C75: September | D75: Zijin Mining | E75: 280 | F75: Copperbelt Minerals | G75: Metals | I75: Congo | J75: Sub-Saharan Africa
A76: =ROW()-6 -> 70 | B76: 2010 | C76: October | D76: HNA | E76: 380 | F76: Offshore Heavy Transports | G76: Transport | H76: Shipping | I76: Norway | J76: Europe
A77: =ROW()-6 -> 71 | B77: 2010 | C77: October | D77: Wuhan Iron and Steel | E77: 800 | F77: Riversdale Mining | G77: Energy | H77: Coal | I77: Mozambique | J77: Sub-Saharan Africa
A78: =ROW()-6 -> 72 | B78: 2010 | C78: October | D78: China Railway Construction | E78: 620 | G78: Transport | H78: Rail | I78: Saudi Arabia | J78: Arab Middle East and North Africa
A79: =ROW()-6 -> 73 | B79: 2010 | C79: November | D79: Huawei, ZTE (Zhongxing Telecommunications Equipment) | E79: 5000 | F79: Sprint | G79: Technology | H79: Telecom | I79: USA | J79: USA
A80: =ROW()-6 -> 74 | B80: 2010 | C80: December | D80: China National Nuclear | E80: 350 | G80: Energy | I80: Timor-Leste | J80: East Asia
A81: =ROW()-6 -> 75 | B81: 2010 | C81: December | D81: China National Machinery Industry (Sinomach) | E81: 1430 | G81: Agriculture | I81: Venezuela | J81: South America
A82: =ROW()-6 -> 76 | B82: 2011 | C82: March | D82: Sinohydro | E82: 1800 | G82: Real estate | H82: Construction | I82: Libya | J82: Arab Middle East and North Africa
A83: =ROW()-6 -> 77 | B83: 2011 | C83: March | D83: China Communications Construction | E83: 1910 | G83: Real estate | H83: Construction | I83: Libya | J83: Arab Middle East and North Africa
A84: =ROW()-6 -> 78 | B84: 2011 | C84: March | D84: Gezhouba | E84: 840 | G84: Real estate | H84: Construction | I84: Libya | J84: Arab Middle East and North Africa
A85: =ROW()-6 -> 79 | B85: 2011 | C85: March | D85: China Railway Construction | E85: 3550 | G85: Transport | H85: Rail | I85: Libya | J85: Arab Middle East and North Africa
A86: =ROW()-6 -> 80 | B86: 2011 | C86: March | D86: MCC | E86: 820 | G86: Real estate | H86: Construction | I86: Libya | J86: Arab Middle East and North Africa
A87: =ROW()-6 -> 81 | B87: 2011 | C87: March | D87: State Construction Engineering | E87: 2680 | G87: Real estate | H87: Construction | I87: Libya | J87: Arab Middle East and North Africa
A88: =ROW()-6 -> 82 | B88: 2011 | C88: March | D88: China National Machinery Industry (Sinomach) | E88: 600 | G88: Real estate | H88: Construction | I88: Libya | J88: Arab Middle East and North Africa
A89: =ROW()-6 -> 83 | B89: 2011 | C89: May | D89: Hawtai Motor | E89: 170 | F89: Spyker | G89: Transport | H89: Autos | I89: Sweden | J89: Europe
A90: =ROW()-6 -> 84 | B90: 2011 | C90: June | D90: China National Petroleum Corp. (CNPC) | E90: 5390 | F90: EnCana | G90: Energy | H90: Gas | I90: Canada | J90: North America
A91: =ROW()-6 -> 85 | B91: 2011 | C91: June | D91: China Railway Engineering, MCC | E91: 400 | F91: Resourcehouse | G91: Metals | I91: Australia | J91: Australia
A92: =ROW()-6 -> 86 | B92: 2011 | C92: June | D92: China Railway Engineering | E92: 450 | F92: Decoma | G92: Transport | H92: Autos | I92: Poland | J92: Europe
A93: =ROW()-6 -> 87 | B93: 2011 | C93: June | D93: Sinosteel | E93: 1990 | G93: Metals | H93: Steel | I93: Australia | J93: Australia | K93: G
A94: =ROW()-6 -> 88 | B94: 2011 | C94: July | D94: Anshan Steel | E94: 170 | F94: Gindalbie | G94: Metals | H94: Steel | I94: Australia | J94: Australia
A95: =ROW()-6 -> 89 | B95: 2011 | C95: September | D95: China Power Investment | E95: 3600 | F95: Asia World Company | G95: Energy | H95: Hydro | I95: Myanmar | J95: East Asia
A96: =ROW()-6 -> 90 | B96: 2011 | C96: September | D96: Sinohydro | E96: 560 | G96: Energy | H96: Hydro | I96: Ethiopia | J96: Sub-Saharan Africa
A97: =ROW()-6 -> 91 | B97: 2011 | C97: October | D97: Anshan Steel | E97: 170 | F97: Steel Development | G97: Metals | H97: Steel | I97: USA | J97: USA | K97: G
A98: =ROW()-6 -> 92 | B98: 2011 | C98: October | D98: Sichuan Hanlong | E98: 150 | F98: Bannerman | G98: Metals | I98: Australia | J98: Australia
A99: =ROW()-6 -> 93 | B99: 2011 | C99: October | D99: Aviation Industry Corp. (AVIC) | E99: 500 | G99: Tourism | I99: Sri Lanka | J99: West Asia | K99: G
A100: =ROW()-6 -> 94 | B100: 2011 | C100: October | D100: China Railway Engineering | E100: 320 | G100: Transport | H100: Rail | I100: Vietnam | J100: East Asia
A101: =ROW()-6 -> 95 | B101: 2011 | C101: November | D101: China National Off-shore Oil (CNOOC) | E101: 7100 | F101: BP | G101: Energy | I101: Argentina | J101: South America
A102: =ROW()-6 -> 96 | B102: 2011 | C102: November | D102: Zhongkun | E102: 200 | G102: Tourism | I102: Iceland | J102: Europe | K102: G
...

Sheet Dataset 1+2
A1: China Global Investment Tracker
A2: © Data compiled by The American Enterprise Institute and The Heritage Foundation. All rights reserved.
A4: Dataset 1 and 2 combined
A5: Year | B5: Month | C5: Investor/Contractor | D5: Quantity in Millions | E5: Share Size | F5: Transaction Party | G5: Sector | H5: Subsector | I5: Country | J5: Region | K5: BRI | L5: Greenfield
A6: 2005 | B6: January | C6: Chinese Academy of Sciences | D6: 1740 | F6: IBM | G6: Technology | I6: USA | J6: USA
A7: 2005 | B7: January | C7: Minmetals | D7: 500 | F7: Cubapetroleo | G7: Metals | I7: Cuba | J7: North America | L7: G
A8: 2005 | B8: January | C8: Sinohydro | D8: 100 | G8: Transport | H8: Aviation | I8: Qatar | J8: Arab Middle East and North Africa
A9: 2005 | B9: February | C9: Sinohydro | D9: 150 | F9: Oman Wastewater Services | G9: Utilities | I9: Oman | J9: Arab Middle East and North Africa
A10: 2005 | B10: February | C10: Sinohydro | D10: 370 | G10: Transport | H10: Autos | I10: Ecuador | J10: South America
A11: 2005 | B11: March | C11: MCC | D11: 670 | E11: 0.85 | F11: Highlands Pacific | G11: Metals | H11: Steel | I11: Papua New Guinea | J11: East Asia | L11: G
A12: 2005 | B12: March | C12: Sinoma | D12: 170 | F12: Riyadh Cement | G12: Real estate | H12: Construction | I12: Saudi Arabia | J12: Arab Middle East and North Africa
A13: 2005 | B13: April | C13: China National Off-shore Oil (CNOOC) | D13: 130 | E13: 0.17 | F13: MEG Energy | G13: Energy | H13: Oil | I13: Canada | J13: North America
A14: 2005 | B14: April | C14: China National Machinery Industry (Sinomach) | D14: 100 | G14: Utilities | I14: Sudan | J14: Arab Middle East and North Africa
A15: 2005 | B15: April | C15: Minmetals, MCC | D15: 240 | G15: Metals | H15: Steel | I15: Brazil | J15: South America
A16: 2005 | B16: May | C16: China National Petroleum Corp. (CNPC) | D16: 390 | F16: SONATRACH | G16: Energy | I16: Algeria | J16: Arab Middle East and North Africa
A17: 2005 | B17: June | C17: China Petroleum and Chemical (Sinopec) | D17: 120 | E17: 0.4 | F17: Synenco | G17: Energy | H17: Oil | I17: Canada | J17: North America | L17: G
A18: 2005 | B18: June | C18: China Railway Construction, China General Technology (Genertec) | D18: 1270 | F18: Cengiz and IC Ictas | G18: Transport | H18: Rail | I18: Turkey | J18: West Asia
A19: 2005 | B19: June | C19: China National Machinery Industry (Sinomach), Sinohydro | D19: 860 | G19: Energy | H19: Coal | I19: Indonesia | J19: East Asia
A20: 2005 | B20: June | C20: MCC | D20: 170 | G20: Transport | H20: Aviation | I20: Mauritania | J20: Arab Middle East and North Africa
A21: 2005 | B21: July | C21: Jiangsu Yuejin | D21: 100 | E21: 1 | F21: MG | G21: Transport | H21: Autos | I21: Britain | J21: Europe
A22: 2005 | B22: July | C22: Sinohydro | D22: 280 | G22: Energy | H22: Hydro | I22: Cambodia | J22: East Asia | L22: G
A23: 2005 | B23: July | C23: China International Trust and Investment (CITIC), Sinohydro | D23: 130 | G23: Energy | H23: Hydro | I23: Myanmar | J23: East Asia
A24: 2005 | B24: August | C24: China National Petroleum Corp. (CNPC) | D24: 4200 | E24: 0.67 | F24: PetroKazakhstan | G24: Energy | H24: Oil | I24: Kazakhstan | J24: West Asia
A25: 2005 | B25: September | C25: China National Petroleum Corp. (CNPC), China Petroleum and Chemical (Sinopec) | D25: 1420 | F25: EnCana | G25: Energy | H25: Oil | I25: Ecuador | J25: South America
A26: 2005 | B26: September | C26: China Investment Corporation (CIC), Beijing Jingdeshun | D26: 200 | G26: Energy | H26: Oil | I26: Mongolia | J26: East Asia | L26: G
A27: 2005 | B27: September | C27: China Petroleum and Chemical (Sinopec) | D27: 350 | E27: 0.45 | F27: Aker Kvaerner | G27: Chemicals | I27: Saudi Arabia | J27: Arab Middle East and North Africa
A28: 2005 | B28: October | C28: Sinosteel | D28: 140 | E28: 0.5 | F28: Midwest | G28: Metals | H28: Steel | I28: Australia | J28: Australia | L28: G
A29: 2005 | B29: October | C29: China National Chemical (ChemChina) | D29: 180 | E29: 1 | F29: Qenos | G29: Chemicals | I29: Australia | J29: Australia
A30: 2005 | B30: October | C30: China Nonferrous | D30: 330 | F30: Kazakhstan Aluminum | G30: Metals | H30: Aluminum | I30: Kazakhstan | J30: West Asia
A31: 2005 | B31: October | C31: China Communications Construction | D31: 200 | G31: Transport | H31: Autos | I31: Indonesia | J31: East Asia
A32: 2005 | B32: November | C32: China North Industries (Norinco) | D32: 120 | F32: Electricite du Laos | G32: Energy | H32: Hydro | I32: Laos | J32: East Asia
A33: 2005 | B33: November | C33: China International Trust and Investment (CITIC) | D33: 1190 | G33: Real estate | H33: Construction | I33: Venezuela | J33: South America
A34: 2005 | B34: December | C34: China National Petroleum Corp. (CNPC) | D34: 290 | E34: 0.16 | F34: Petro-Canada | G34: Energy | H34: Oil | I34: Syria | J34: Arab Middle East and North Africa
A35: 2005 | B35: December | C35: Zhejiang Holley | D35: 150 | E35: 0.75 | F35: Amata | G35: Other | H35: Industry | I35: Thailand | J35: East Asia | L35: G
A36: 2005 | B36: December | C36: China International Trust and Investment (CITIC), Aluminum Corporation of China (Chinalco) | D36: 900 | F36: South Iran Aluminum | G36: Metals | H36: Aluminum | I36: Iran | J36: West Asia
A37: 2005 | B37: December | C37: Sinoma | D37: 580 | F37: Saudi Cement | G37: Real estate | H37: Construction | I37: Saudi Arabia | J37: Arab Middle East and North Africa
A38: 2005 | B38: December | C38: China International Trust and Investment (CITIC) | D38: 430 | F38: Brazil Power | G38: Energy | H38: Coal | I38: Brazil | J38: South America
A39: 2005 | B39: December | C39: Sinohydro | D39: 210 | G39: Agriculture | I39: Algeria | J39: Arab Middle East and North Africa
A40: 2005 | B40: December | C40: China Communications Construction | D40: 210 | G40: Transport | H40: Autos | I40: Angola | J40: Sub-Saharan Africa
A41: 2005 | B41: December | C41: China National Nuclear | D41: 860 | G41: Energy | I41: Pakistan | J41: West Asia
A42: 2006 | B42: January | C42: China National Off-shore Oil (CNOOC) | D42: 2270 | E42: 0.45 | F42: South African Petroleum | G42: Energy | I42: Nigeria | J42: Sub-Saharan Africa
A43: 2006 | B43: January | C43: China National Chemical (ChemChina) | D43: 480 | E43: 1 | F43: Adisseo | G43: Agriculture | I43: France | J43: Europe
A44: 2006 | B44: January | C44: China National Petroleum Corp. (CNPC) | D44: 480 | E44: 1 | G44: Energy | H44: Oil | I44: Chad | J44: Sub-Saharan Africa
A45: 2006 | B45: March | C45: China International Trust and Investment (CITIC) | D45: 2920 | F45: Mineralogy | G45: Metals | H45: Steel | I45: Australia | J45: Australia | L45: G
A46: 2006 | B46: April | C46: Shanghai Municipal Government | D46: 1300 | E46: 1 | G46: Real estate | H46: Property | I46: Russian Federation | J46: West Asia | L46: G
A47: 2006 | B47: May | C47: MCC | D47: 120 | E47: 1 | G47: Other | H47: Timber | I47: Russian Federation | J47: West Asia | L47: G
A48: 2006 | B48: May | C48: China Petroleum and Chemical (Sinopec) | D48: 740 | E48: 0.75 | F48: Sonangol | G48: Energy | H48: Oil | I48: Angola | J48: Sub-Saharan Africa | L48: G
A49: 2006 | B49: June | C49: China Petroleum and Chemical (Sinopec) | D49: 3490 | E49: 0.49 | F49: Rosneft | G49: Energy | I49: Russian Federation | J49: West Asia
A50: 2006 | B50: July | C50: China International Trust and Investment (CITIC) | D50: 100 | E50: 0.51 | F50: Kuwait Petroleum | G50: Energy | H50: Oil | I50: Indonesia | J50: East Asia
A51: 2006 | B51: July | C51: China National Petroleum Corp. (CNPC) | D51: 500 | F51: Rosneft | G51: Energy | I51: Russian Federation | J51: West Asia
A52: 2006 | B52: August | C52: Wuxi Suntech | D52: 110 | E52: 0.67 | F52: MSK | G52: Energy | H52: Alternative | I52: Japan | J52: East Asia
A53: 2006 | B53: September | C53: China Petroleum and Chemical (Sinopec) | D53: 430 | E53: 0.5 | F53: Omimex | G53: Energy | H53: Oil | I53: Colombia | J53: South America
A54: 2006 | B54: October | C54: Jiangxi Copper | D54: 110 | E54: 0.75 | F54: bcMetals | G54: Metals | H54: Copper | I54: Canada | J54: North America | L54: G
A55: 2006 | B55: October | C55: China International Trust and Investment (CITIC), Aluminum Corporation of China (Chinalco) | D55: 940 | G55: Metals | H55: Aluminum | I55: Egypt | J55: Arab Middle East and North Africa | L55: G
A56: 2006 | B56: October | C56: China International Trust and Investment (CITIC) | D56: 1910 | F56: Nations Energy | G56: Energy | I56: Kazakhstan | J56: West Asia
A57: 2006 | B57: November | C57: China Development Bank | D57: 800 | E57: 0.01 | F57: Anglo-American | G57: Metals | I57: Britain | J57: Europe
A58: 2006 | B58: November | C58: Sinosteel | D58: 230 | E58: 0.5 | F58: Samancor Chrome | G58: Metals | H58: Steel | I58: South Africa | J58: Sub-Saharan Africa
A59: 2006 | B59: November | C59: China Nonferrous | D59: 310 | E59: 1 | G59: Metals | H59: Copper | I59: Zambia | J59: Sub-Saharan Africa | L59: G
A60: 2006 | B60: November | C60: Ex-Im Bank | D60: 1160 | G60: Metals | I60: Democratic Republic of the Congo | J60: Sub-Saharan Africa
A61: 2006 | B61: November | C61: Three Gorges | D61: 140 | E61: 0.9 | F61: EDL | G61: Energy | H61: Hydro | I61: Laos | J61: East Asia | L61: G
A62: 2006 | B62: December | C62: Bank of China | D62: 970 | E62: 1 | F62: WestLB, Singapore Air, local government | G62: Transport | H62: Aviation | I62: Singapore | J62: East Asia
A63: 2006 | B63: December | C63: Sichuan Changhong | D63: 100 | E63: 0.75 | F63: Sterope investments | G63: Finance | H63: Investment | I63: Netherlands | J63: Europe
A64: 2006 | B64: January | C64: State Construction Engineering | D64: 300 | F64: Dubai Properties | G64: Real estate | H64: Construction | I64: UAE | J64: Arab Middle East and North Africa
A65: 2006 | B65: January | C65: China North Industries (Norinco) | D65: 310 | F65: Tehran Rail | G65: Transport | H65: Rail | I65: Iran | J65: West Asia
A66: 2006 | B66: February | C66: Sinohydro | D66: 540 | G66: Real estate | H66: Construction | I66: Qatar | J66: Arab Middle East and North Africa
A67: 2006 | B67: March | C67: China National Machinery Industry (Sinomach) | D67: 460 | G67: Energy | H67: Coal | I67: Sri Lanka | J67: West Asia
A68: 2006 | B68: April | C68: China Petroleum and Chemical (Sinopec) | D68: 1290 | F68: Petrobras | G68: Energy | H68: Gas | I68: Brazil | J68: South America
A69: 2006 | B69: May | C69: China International Trust and Investment (CITIC), China Railway Construction | D69: 6250 | G69: Transport | H69: Autos | I69: Algeria | J69: Arab Middle East and North Africa
A70: 2006 | B70: May | C70: Shandong Electric Power Construction III | D70: 1500 | F70: Vedanta | G70: Energy | H70: Coal | I70: India | J70: West Asia
A71: 2006 | B71: May | C71: China Power Engineering Consulting | D71: 110 | G71: Energy | I71: Nigeria | J71: Sub-Saharan Africa
A72: 2006 | B72: June | C72: Tebian Electric Apparatus (TBEA) | D72: 400 | G72: Energy | I72: Tajikistan | J72: West Asia
A73: 2006 | B73: June | C73: Weihai International Economic | D73: 160 | G73: Transport | H73: Aviation | I73: Congo | J73: Sub-Saharan Africa
A74: 2006 | B74: June | C74: Sinoma | D74: 260 | F74: Arab Yemen Cement | G74: Real estate | H74: Construction | I74: Yemen | J74: Arab Middle East and North Africa
A75: 2006 | B75: June | C75: Jiangsu International Cooperation Corp | D75: 170 | G75: Utilities | I75: Botswana | J75: Sub-Saharan Africa
A76: 2006 | B76: July | C76: China Communications Construction | D76: 300 | G76: Transport | H76: Autos | I76: Tajikistan | J76: West Asia
A77: 2006 | B77: July | C77: State Construction Engineering | D77: 260 | G77: Transport | H77: Aviation | I77: Algeria | J77: Arab Middle East and North Africa
A78: 2006 | B78: July | C78: China Petroleum and Chemical (Sinopec) | D78: 2840 | G78: Energy | H78: Oil | I78: Iran | J78: West Asia
A79: 2006 | B79: July | C79: Dongfang Electric | D79: 330 | E79: 0.55 | F79: Marubeni | G79: Energy | H79: Coal | I79: Vietnam | J79: East Asia
A80: 2006 | B80: September | C80: ZTE (Zhongxing Telecommunications Equipment), Huawei, China Communications Construction | D80: 2400 | F80: Ethiopia Telecom | G80: Technology | H80: Telecom | I80: Ethiopia | J80: Sub-Saharan Africa
A81: 2006 | B81: September | C81: Huawei | D81: 550 | F81: Ufone | G81: Technology | H81: Telecom | I81: Pakistan | J81: West Asia
A82: 2006 | B82: November | C82: China International Trust and Investment (CITIC) | D82: 340 | F82: ThyssenKrupp | G82: Metals | H82: Steel | I82: Brazil | J82: South America
A83: 2006 | B83: November | C83: China Communications Construction | D83: 490 | G83: Transport | H83: Autos | I83: Pakistan | J83: West Asia
A84: 2006 | B84: November | C84: China General Technology (Genertec) | D84: 220 | G84: Real estate | H84: Construction | I84: Yemen | J84: Arab Middle East and North Africa
A85: 2006 | B85: November | C85: China National Chemical Engineering | D85: 180 | F85: Bosowa | G85: Energy | H85: Coal | I85: Indonesia | J85: East Asia
A86: 2006 | B86: November | C86: China National Petroleum Corp. (CNPC) | D86: 430 | G86: Agriculture | I86: Vietnam | J86: East Asia
A87: 2006 | B87: December | C87: Sinohydro | D87: 130 | G87: Transport | H87: Autos | I87: Ethiopia | J87: Sub-Saharan Africa
A88: 2006 | B88: December | C88: Harbin Electric | D88: 520 | G88: Energy | H88: Coal | I88: Indonesia | J88: East Asia
A89: 2006 | B89: December | C89: Huadian | D89: 250 | G89: Energy | H89: Hydro | I89: Indonesia | J89: East Asia
A90: 2006 | B90: December | C90: Shanghai Electric | D90: 260 | F90: Truba Alam Manunggal | G90: Energy | H90: Coal | I90: Indonesia | J90: East Asia
A91: 2006 | B91: December | C91: Sinoma | D91: 130 | F91: Mugher Cement | G91: Real estate | H91: Construction | I91: Ethiopia | J91: Sub-Saharan Africa
A92: 2007 | B92: January | C92: China National Chemical (ChemChina) | D92: 700 | F92: Rhodia | G92: Chemicals | I92: France | J92: Europe
A93: 2007 | B93: January | C93: China Mobile | D93: 280 | E93: 0.89 | F93: Millicom | G93: Technology | H93: Telecom | I93: Pakistan | J93: West Asia
A94: 2007 | B94: January | C94: China National Petroleum Corp. (CNPC) | D94: 200 | E94: 0.5 | F94: EnCana | G94: Energy | H94: Oil | I94: Chad | J94: Sub-Saharan Africa
A95: 2007 | B95: February | C95: Zijin Mining, China Nonferrous, Xiamen C&D | D95: 190 | E95: 45%, 35%, 20% | F95: Monterrico | G95: Metals | H95: Copper | I95: Peru | J95: South America
A96: 2007 | B96: February | C96: China Petroleum and Chemical (Sinopec) | D96: 100 | F96: Syntroleum | G96: Energy | I96: USA | J96: USA
A97: 2007 | B97: March | C97: Sinosteel | D97: 250 | G97: Metals | H97: Steel | I97: India | J97: West Asia | L97: G
A98: 2007 | B98: May | C98: China Investment Corporation (CIC) | D98: 3030 | E98: 0.09 | F98: Blackstone | G98: Finance | H98: Investment | I98: USA | J98: USA
A99: 2007 | B99: May | C99: LinkGlobal Logistics | D99: 130 | G99: Transport | H99: Aviation | I99: Germany | J99: Europe
A100: 2007 | B100: May | C100: China Mobile | D100: 180 | E100: 0.11 | F100: Paktel | G100: Technology | H100: Telecom | I100: Pakistan | J100: West Asia
A101: 2007 | B101: June | C101: Aluminum Corporation of China (Chinalco) | D101: 790 | E101: 1 | F101: Peru Copper | G101: Metals | H101: Copper | I101: Peru | J101: South America
...

Sheet FDI Stock Analysis
A1: China FDI annual analysis from Dataset 1
A2: Flows are annual sums of Quantity in Millions. Stock is a gross cumulative recorded-investment proxy, not an official FDI position measure.
A4: By destination country
A5: Annual flow (USD millions) | B5: Afghanistan | C5: Algeria | D5: Angola | E5: Antigua and Barbuda | F5: Argentina | G5: Australia | H5: Austria | I5: Azerbaijan | J5: Bahamas | K5: Bangladesh | L5: Belarus | M5: Belgium | N5: Bolivia | O5: Bosnia | P5: Botswana | Q5: Brazil | R5: Britain | S5: Brunei | T5: Bulgaria | U5: Cambodia | V5: Cameroon | W5: Canada | X5: Chad | Y5: Chile | Z5: Colombia | AA5: Congo | AB5: Croatia | AC5: Cuba | AD5: Cyprus | AE5: Czech Republic | AF5: Democratic Republic of the Congo | AG5: Denmark | AH5: Djibouti | AI5: Ecuador | AJ5: Egypt | AK5: Eritrea | AL5: Ethiopia | AM5: Finland | AN5: France | AO5: Gabon | AP5: Georgia | AQ5: Germany | AR5: Ghana | AS5: Greece | AT5: Guinea | AU5: Guinea-Bissau | AV5: Guyana | AW5: Hungary | AX5: India | AY5: Indonesia | AZ5: Iran | BA5: Iraq | BB5: Ireland | BC5: Israel | BD5: Italy | BE5: Ivory Coast | BF5: Jamaica | BG5: Japan | BH5: Jordan | BI5: Kazakhstan | BJ5: Kenya | BK5: Kuwait | BL5: Kyrgyzstan | BM5: Laos | BN5: Liberia | BO5: Luxembourg | BP5: Madagascar | BQ5: Malawi | BR5: Malaysia | BS5: Maldives | BT5: Mali | BU5: Malta | BV5: Mauritius | BW5: Mexico | BX5: Mongolia | BY5: Montenegro | BZ5: Morocco | CA5: Mozambique | CB5: Myanmar | CC5: Namibia | CD5: Nepal | CE5: Netherlands | CF5: New Zealand | CG5: Nicaragua | CH5: Niger | CI5: Nigeria | CJ5: North Korea | CK5: Norway | CL5: Oman | CM5: Pakistan | CN5: Panama | CO5: Papua New Guinea | CP5: Peru | CQ5: Philippines | CR5: Poland | CS5: Portugal | CT5: Qatar | CU5: Russian Federation | CV5: Rwanda | CW5: Samoa | CX5: Sao Tome | CY5: Saudi Arabia | CZ5: Serbia | DA5: Sierra Leone | DB5: Singapore | DC5: Slovakia | DD5: Slovenia | DE5: Solomon Islands | DF5: South Africa | DG5: South Korea | DH5: Spain | DI5: Sri Lanka | DJ5: Sudan | DK5: Suriname | DL5: Sweden | DM5: Switzerland | DN5: Syria | DO5: Taiwan | DP5: Tajikistan | DQ5: Tanzania | DR5: Thailand | DS5: Togo | DT5: Trinidad-Tobago | DU5: Tunisia | DV5: Turkey | DW5: Turkmenistan | DX5: UAE | DY5: USA | DZ5: Uganda | EA5: Ukraine | EB5: Uzbekistan | EC5: Venezuela | ED5: Vietnam | EE5: Yemen | EF5: Zambia | EG5: Zimbabwe
A6: 2005 | B6: =SUMIFS('Dataset 1'!$E$7:$E$2506,'Dataset 1'!$B$7:$B$2506,$A6,'Dataset 1'!$J$7:$J$2506,B$5) -> 0 | C6: =SUMIFS('Dataset 1'!$E$7:$E$2506,'Dataset 1'!$B$7:$B$2506,$A6,'Dataset 1'!$J$7:$J$2506,C$5) -> 0 | D6: =SUMIFS('Dataset 1'!$E$7:$E$2506,'Dataset 1'!$B$7:$B$2506,$A6,'Dataset 1'!$J$7:$J$2506,D$5) -> 0 | E6: =SUMIFS('Dataset 1'!$E$7:$E$2506,'Dataset 1'!$B$7:$B$2506,$A6,'Dataset 1'!$J$7:$J$2506,E$5) -> 0 | F6: =SUMIFS('Dataset 1'!$E$7:$E$2506,'Dataset 1'!$B$7:$B$2506,$A6,'Dataset 1'!$J$7:$J$2506,F$5) -> 0 | G6: =SUMIFS('Dataset 1'!$E$7:$E$2506,'Dataset 1'!$B$7:$B$2506,$A6,'Dataset 1'!$J$7:$J$2506,G$5) -> 320 | H6: =SUMIFS('Dataset 1'!$E$7:$E$2506,'Dataset 1'!$B$7:$B$2506,$A6,'Dataset 1'!$J$7:$J$2506,H$5) -> 0 | I6: =SUMIFS('Dataset 1'!$E$7:$E$2506,'Dataset 1'!$B$7:$B$2506,$A6,'Dataset 1'!$J$7:$J$2506,I$5) -> 0 | ... EG6: =SUMIFS('Dataset 1'!$E$7:$E$2506,'Dataset 1'!$B$7:$B$2506,$A6,'Dataset 1'!$J$7:$J$2506,EG$5) -> 0
A7: 2006 | B7: =SUMIFS('Dataset 1'!$E$7:$E$2506,'Dataset 1'!$B$7:$B$2506,$A7,'Dataset 1'!$J$7:$J$2506,B$5) -> 0 | C7: =SUMIFS('Dataset 1'!$E$7:$E$2506,'Dataset 1'!$B$7:$B$2506,$A7,'Dataset 1'!$J$7:$J$2506,C$5) -> 0 | D7: =SUMIFS('Dataset 1'!$E$7:$E$2506,'Dataset 1'!$B$7:$B$2506,$A7,'Dataset 1'!$J$7:$J$2506,D$5) -> 740 | E7: =SUMIFS('Dataset 1'!$E$7:$E$2506,'Dataset 1'!$B$7:$B$2506,$A7,'Dataset 1'!$J$7:$J$2506,E$5) -> 0 | F7: =SUMIFS('Dataset 1'!$E$7:$E$2506,'Dataset 1'!$B$7:$B$2506,$A7,'Dataset 1'!$J$7:$J$2506,F$5) -> 0 | G7: =SUMIFS('Dataset 1'!$E$7:$E$2506,'Dataset 1'!$B$7:$B$2506,$A7,'Dataset 1'!$J$7:$J$2506,G$5) -> 2920 | H7: =SUMIFS('Dataset 1'!$E$7:$E$2506,'Dataset 1'!$B$7:$B$2506,$A7,'Dataset 1'!$J$7:$J$2506,H$5) -> 0 | I7: =SUMIFS('Dataset 1'!$E$7:$E$2506,'Dataset 1'!$B$7:$B$2506,$A7,'Dataset 1'!$J$7:$J$2506,I$5) -> 0 | ... EG7: =SUMIFS('Dataset 1'!$E$7:$E$2506,'Dataset 1'!$B$7:$B$2506,$A7,'Dataset 1'!$J$7:$J$2506,EG$5) -> 0
A8: 2007 | B8: =SUMIFS('Dataset 1'!$E$7:$E$2506,'Dataset 1'!$B$7:$B$2506,$A8,'Dataset 1'!$J$7:$J$2506,B$5) -> 2520 | C8: =SUMIFS('Dataset 1'!$E$7:$E$2506,'Dataset 1'!$B$7:$B$2506,$A8,'Dataset 1'!$J$7:$J$2506,C$5) -> 0 | D8: =SUMIFS('Dataset 1'!$E$7:$E$2506,'Dataset 1'!$B$7:$B$2506,$A8,'Dataset 1'!$J$7:$J$2506,D$5) -> 0 | E8: =SUMIFS('Dataset 1'!$E$7:$E$2506,'Dataset 1'!$B$7:$B$2506,$A8,'Dataset 1'!$J$7:$J$2506,E$5) -> 0 | F8: =SUMIFS('Dataset 1'!$E$7:$E$2506,'Dataset 1'!$B$7:$B$2506,$A8,'Dataset 1'!$J$7:$J$2506,F$5) -> 0 | G8: =SUMIFS('Dataset 1'!$E$7:$E$2506,'Dataset 1'!$B$7:$B$2506,$A8,'Dataset 1'!$J$7:$J$2506,G$5) -> 430 | H8: =SUMIFS('Dataset 1'!$E$7:$E$2506,'Dataset 1'!$B$7:$B$2506,$A8,'Dataset 1'!$J$7:$J$2506,H$5) -> 0 | I8: =SUMIFS('Dataset 1'!$E$7:$E$2506,'Dataset 1'!$B$7:$B$2506,$A8,'Dataset 1'!$J$7:$J$2506,I$5) -> 0 | ... EG8: =SUMIFS('Dataset 1'!$E$7:$E$2506,'Dataset 1'!$B$7:$B$2506,$A8,'Dataset 1'!$J$7:$J$2506,EG$5) -> 100
A9: 2008 | B9: =SUMIFS('Dataset 1'!$E$7:$E$2506,'Dataset 1'!$B$7:$B$2506,$A9,'Dataset 1'!$J$7:$J$2506,B$5) -> 0 | C9: =SUMIFS('Dataset 1'!$E$7:$E$2506,'Dataset 1'!$B$7:$B$2506,$A9,'Dataset 1'!$J$7:$J$2506,C$5) -> 0 | D9: =SUMIFS('Dataset 1'!$E$7:$E$2506,'Dataset 1'!$B$7:$B$2506,$A9,'Dataset 1'!$J$7:$J$2506,D$5) -> 0 | E9: =SUMIFS('Dataset 1'!$E$7:$E$2506,'Dataset 1'!$B$7:$B$2506,$A9,'Dataset 1'!$J$7:$J$2506,E$5) -> 0 | F9: =SUMIFS('Dataset 1'!$E$7:$E$2506,'Dataset 1'!$B$7:$B$2506,$A9,'Dataset 1'!$J$7:$J$2506,F$5) -> 0 | G9: =SUMIFS('Dataset 1'!$E$7:$E$2506,'Dataset 1'!$B$7:$B$2506,$A9,'Dataset 1'!$J$7:$J$2506,G$5) -> 16250 | H9: =SUMIFS('Dataset 1'!$E$7:$E$2506,'Dataset 1'!$B$7:$B$2506,$A9,'Dataset 1'!$J$7:$J$2506,H$5) -> 0 | I9: =SUMIFS('Dataset 1'!$E$7:$E$2506,'Dataset 1'!$B$7:$B$2506,$A9,'Dataset 1'!$J$7:$J$2506,I$5) -> 0 | ... EG9: =SUMIFS('Dataset 1'!$E$7:$E$2506,'Dataset 1'!$B$7:$B$2506,$A9,'Dataset 1'!$J$7:$J$2506,EG$5) -> 0
A10: 2009 | B10: =SUMIFS('Dataset 1'!$E$7:$E$2506,'Dataset 1'!$B$7:$B$2506,$A10,'Dataset 1'!$J$7:$J$2506,B$5) -> 0 | C10: =SUMIFS('Dataset 1'!$E$7:$E$2506,'Dataset 1'!$B$7:$B$2506,$A10,'Dataset 1'!$J$7:$J$2506,C$5) -> 0 | D10: =SUMIFS('Dataset 1'!$E$7:$E$2506,'Dataset 1'!$B$7:$B$2506,$A10,'Dataset 1'!$J$7:$J$2506,D$5) -> 0 | E10: =SUMIFS('Dataset 1'!$E$7:$E$2506,'Dataset 1'!$B$7:$B$2506,$A10,'Dataset 1'!$J$7:$J$2506,E$5) -> 0 | F10: =SUMIFS('Dataset 1'!$E$7:$E$2506,'Dataset 1'!$B$7:$B$2506,$A10,'Dataset 1'!$J$7:$J$2506,F$5) -> 0 | G10: =SUMIFS('Dataset 1'!$E$7:$E$2506,'Dataset 1'!$B$7:$B$2506,$A10,'Dataset 1'!$J$7:$J$2506,G$5) -> 9130 | H10: =SUMIFS('Dataset 1'!$E$7:$E$2506,'Dataset 1'!$B$7:$B$2506,$A10,'Dataset 1'!$J$7:$J$2506,H$5) -> 140 | I10: =SUMIFS('Dataset 1'!$E$7:$E$2506,'Dataset 1'!$B$7:$B$2506,$A10,'Dataset 1'!$J$7:$J$2506,I$5) -> 0 | ... EG10: =SUMIFS('Dataset 1'!$E$7:$E$2506,'Dataset 1'!$B$7:$B$2506,$A10,'Dataset 1'!$J$7:$J$2506,EG$5) -> 0
A11: 2010 | B11: =SUMIFS('Dataset 1'!$E$7:$E$2506,'Dataset 1'!$B$7:$B$2506,$A11,'Dataset 1'!$J$7:$J$2506,B$5) -> 0 | C11: =SUMIFS('Dataset 1'!$E$7:$E$2506,'Dataset 1'!$B$7:$B$2506,$A11,'Dataset 1'!$J$7:$J$2506,C$5) -> 0 | D11: =SUMIFS('Dataset 1'!$E$7:$E$2506,'Dataset 1'!$B$7:$B$2506,$A11,'Dataset 1'!$J$7:$J$2506,D$5) -> 0 | E11: =SUMIFS('Dataset 1'!$E$7:$E$2506,'Dataset 1'!$B$7:$B$2506,$A11,'Dataset 1'!$J$7:$J$2506,E$5) -> 0 | F11: =SUMIFS('Dataset 1'!$E$7:$E$2506,'Dataset 1'!$B$7:$B$2506,$A11,'Dataset 1'!$J$7:$J$2506,F$5) -> 5680 | G11: =SUMIFS('Dataset 1'!$E$7:$E$2506,'Dataset 1'!$B$7:$B$2506,$A11,'Dataset 1'!$J$7:$J$2506,G$5) -> 3340 | H11: =SUMIFS('Dataset 1'!$E$7:$E$2506,'Dataset 1'!$B$7:$B$2506,$A11,'Dataset 1'!$J$7:$J$2506,H$5) -> 0 | I11: =SUMIFS('Dataset 1'!$E$7:$E$2506,'Dataset 1'!$B$7:$B$2506,$A11,'Dataset 1'!$J$7:$J$2506,I$5) -> 0 | ... EG11: =SUMIFS('Dataset 1'!$E$7:$E$2506,'Dataset 1'!$B$7:$B$2506,$A11,'Dataset 1'!$J$7:$J$2506,EG$5) -> 0
A12: 2011 | B12: =SUMIFS('Dataset 1'!$E$7:$E$2506,'Dataset 1'!$B$7:$B$2506,$A12,'Dataset 1'!$J$7:$J$2506,B$5) -> 400 | C12: =SUMIFS('Dataset 1'!$E$7:$E$2506,'Dataset 1'!$B$7:$B$2506,$A12,'Dataset 1'!$J$7:$J$2506,C$5) -> 0 | D12: =SUMIFS('Dataset 1'!$E$7:$E$2506,'Dataset 1'!$B$7:$B$2506,$A12,'Dataset 1'!$J$7:$J$2506,D$5) -> 2170 | E12: =SUMIFS('Dataset 1'!$E$7:$E$2506,'Dataset 1'!$B$7:$B$2506,$A12,'Dataset 1'!$J$7:$J$2506,E$5) -> 0 | F12: =SUMIFS('Dataset 1'!$E$7:$E$2506,'Dataset 1'!$B$7:$B$2506,$A12,'Dataset 1'!$J$7:$J$2506,F$5) -> 1280 | G12: =SUMIFS('Dataset 1'!$E$7:$E$2506,'Dataset 1'!$B$7:$B$2506,$A12,'Dataset 1'!$J$7:$J$2506,G$5) -> 9880 | H12: =SUMIFS('Dataset 1'!$E$7:$E$2506,'Dataset 1'!$B$7:$B$2506,$A12,'Dataset 1'!$J$7:$J$2506,H$5) -> 140 | I12: =SUMIFS('Dataset 1'!$E$7:$E$2506,'Dataset 1'!$B$7:$B$2506,$A12,'Dataset 1'!$J$7:$J$2506,I$5) -> 0 | ... EG12: =SUMIFS('Dataset 1'!$E$7:$E$2506,'Dataset 1'!$B$7:$B$2506,$A12,'Dataset 1'!$J$7:$J$2506,EG$5) -> 500
A13: 2012 | B13: =SUMIFS('Dataset 1'!$E$7:$E$2506,'Dataset 1'!$B$7:$B$2506,$A13,'Dataset 1'!$J$7:$J$2506,B$5) -> 0 | C13: =SUMIFS('Dataset 1'!$E$7:$E$2506,'Dataset 1'!$B$7:$B$2506,$A13,'Dataset 1'!$J$7:$J$2506,C$5) -> 0 | D13: =SUMIFS('Dataset 1'!$E$7:$E$2506,'Dataset 1'!$B$7:$B$2506,$A13,'Dataset 1'!$J$7:$J$2506,D$5) -> 0 | E13: =SUMIFS('Dataset 1'!$E$7:$E$2506,'Dataset 1'!$B$7:$B$2506,$A13,'Dataset 1'!$J$7:$J$2506,E$5) -> 0 | F13: =SUMIFS('Dataset 1'!$E$7:$E$2506,'Dataset 1'!$B$7:$B$2506,$A13,'Dataset 1'!$J$7:$J$2506,F$5) -> 0 | G13: =SUMIFS('Dataset 1'!$E$7:$E$2506,'Dataset 1'!$B$7:$B$2506,$A13,'Dataset 1'!$J$7:$J$2506,G$5) -> 9080 | H13: =SUMIFS('Dataset 1'!$E$7:$E$2506,'Dataset 1'!$B$7:$B$2506,$A13,'Dataset 1'!$J$7:$J$2506,H$5) -> 0 | I13: =SUMIFS('Dataset 1'!$E$7:$E$2506,'Dataset 1'!$B$7:$B$2506,$A13,'Dataset 1'!$J$7:$J$2506,I$5) -> 0 | ... EG13: =SUMIFS('Dataset 1'!$E$7:$E$2506,'Dataset 1'!$B$7:$B$2506,$A13,'Dataset 1'!$J$7:$J$2506,EG$5) -> 0
A14: 2013 | B14: =SUMIFS('Dataset 1'!$E$7:$E$2506,'Dataset 1'!$B$7:$B$2506,$A14,'Dataset 1'!$J$7:$J$2506,B$5) -> 0 | C14: =SUMIFS('Dataset 1'!$E$7:$E$2506,'Dataset 1'!$B$7:$B$2506,$A14,'Dataset 1'!$J$7:$J$2506,C$5) -> 0 | D14: =SUMIFS('Dataset 1'!$E$7:$E$2506,'Dataset 1'!$B$7:$B$2506,$A14,'Dataset 1'!$J$7:$J$2506,D$5) -> 2120 | E14: =SUMIFS('Dataset 1'!$E$7:$E$2506,'Dataset 1'!$B$7:$B$2506,$A14,'Dataset 1'!$J$7:$J$2506,E$5) -> 0 | F14: =SUMIFS('Dataset 1'!$E$7:$E$2506,'Dataset 1'!$B$7:$B$2506,$A14,'Dataset 1'!$J$7:$J$2506,F$5) -> 120 | G14: =SUMIFS('Dataset 1'!$E$7:$E$2506,'Dataset 1'!$B$7:$B$2506,$A14,'Dataset 1'!$J$7:$J$2506,G$5) -> 9060 | H14: =SUMIFS('Dataset 1'!$E$7:$E$2506,'Dataset 1'!$B$7:$B$2506,$A14,'Dataset 1'!$J$7:$J$2506,H$5) -> 0 | I14: =SUMIFS('Dataset 1'!$E$7:$E$2506,'Dataset 1'!$B$7:$B$2506,$A14,'Dataset 1'!$J$7:$J$2506,I$5) -> 0 | ... EG14: =SUMIFS('Dataset 1'!$E$7:$E$2506,'Dataset 1'!$B$7:$B$2506,$A14,'Dataset 1'!$J$7:$J$2506,EG$5) -> 0
A15: 2014 | B15: =SUMIFS('Dataset 1'!$E$7:$E$2506,'Dataset 1'!$B$7:$B$2506,$A15,'Dataset 1'!$J$7:$J$2506,B$5) -> 0 | C15: =SUMIFS('Dataset 1'!$E$7:$E$2506,'Dataset 1'!$B$7:$B$2506,$A15,'Dataset 1'!$J$7:$J$2506,C$5) -> 0 | D15: =SUMIFS('Dataset 1'!$E$7:$E$2506,'Dataset 1'!$B$7:$B$2506,$A15,'Dataset 1'!$J$7:$J$2506,D$5) -> 120 | E15: =SUMIFS('Dataset 1'!$E$7:$E$2506,'Dataset 1'!$B$7:$B$2506,$A15,'Dataset 1'!$J$7:$J$2506,E$5) -> 740 | F15: =SUMIFS('Dataset 1'!$E$7:$E$2506,'Dataset 1'!$B$7:$B$2506,$A15,'Dataset 1'!$J$7:$J$2506,F$5) -> 0 | G15: =SUMIFS('Dataset 1'!$E$7:$E$2506,'Dataset 1'!$B$7:$B$2506,$A15,'Dataset 1'!$J$7:$J$2506,G$5) -> 10060 | H15: =SUMIFS('Dataset 1'!$E$7:$E$2506,'Dataset 1'!$B$7:$B$2506,$A15,'Dataset 1'!$J$7:$J$2506,H$5) -> 0 | I15: =SUMIFS('Dataset 1'!$E$7:$E$2506,'Dataset 1'!$B$7:$B$2506,$A15,'Dataset 1'!$J$7:$J$2506,I$5) -> 0 | ... EG15: =SUMIFS('Dataset 1'!$E$7:$E$2506,'Dataset 1'!$B$7:$B$2506,$A15,'Dataset 1'!$J$7:$J$2506,EG$5) -> 250
A16: 2015 | B16: =SUMIFS('Dataset 1'!$E$7:$E$2506,'Dataset 1'!$B$7:$B$2506,$A16,'Dataset 1'!$J$7:$J$2506,B$5) -> 0 | C16: =SUMIFS('Dataset 1'!$E$7:$E$2506,'Dataset 1'!$B$7:$B$2506,$A16,'Dataset 1'!$J$7:$J$2506,C$5) -> 0 | D16: =SUMIFS('Dataset 1'!$E$7:$E$2506,'Dataset 1'!$B$7:$B$2506,$A16,'Dataset 1'!$J$7:$J$2506,D$5) -> 0 | E16: =SUMIFS('Dataset 1'!$E$7:$E$2506,'Dataset 1'!$B$7:$B$2506,$A16,'Dataset 1'!$J$7:$J$2506,E$5) -> 0 | F16: =SUMIFS('Dataset 1'!$E$7:$E$2506,'Dataset 1'!$B$7:$B$2506,$A16,'Dataset 1'!$J$7:$J$2506,F$5) -> 300 | G16: =SUMIFS('Dataset 1'!$E$7:$E$2506,'Dataset 1'!$B$7:$B$2506,$A16,'Dataset 1'!$J$7:$J$2506,G$5) -> 10990 | H16: =SUMIFS('Dataset 1'!$E$7:$E$2506,'Dataset 1'!$B$7:$B$2506,$A16,'Dataset 1'!$J$7:$J$2506,H$5) -> 0 | I16: =SUMIFS('Dataset 1'!$E$7:$E$2506,'Dataset 1'!$B$7:$B$2506,$A16,'Dataset 1'!$J$7:$J$2506,I$5) -> 0 | ... EG16: =SUMIFS('Dataset 1'!$E$7:$E$2506,'Dataset 1'!$B$7:$B$2506,$A16,'Dataset 1'!$J$7:$J$2506,EG$5) -> 0
A17: 2016 | B17: =SUMIFS('Dataset 1'!$E$7:$E$2506,'Dataset 1'!$B$7:$B$2506,$A17,'Dataset 1'!$J$7:$J$2506,B$5) -> 0 | C17: =SUMIFS('Dataset 1'!$E$7:$E$2506,'Dataset 1'!$B$7:$B$2506,$A17,'Dataset 1'!$J$7:$J$2506,C$5) -> 0 | D17: =SUMIFS('Dataset 1'!$E$7:$E$2506,'Dataset 1'!$B$7:$B$2506,$A17,'Dataset 1'!$J$7:$J$2506,D$5) -> 0 | E17: =SUMIFS('Dataset 1'!$E$7:$E$2506,'Dataset 1'!$B$7:$B$2506,$A17,'Dataset 1'!$J$7:$J$2506,E$5) -> 0 | F17: =SUMIFS('Dataset 1'!$E$7:$E$2506,'Dataset 1'!$B$7:$B$2506,$A17,'Dataset 1'!$J$7:$J$2506,F$5) -> 290 | G17: =SUMIFS('Dataset 1'!$E$7:$E$2506,'Dataset 1'!$B$7:$B$2506,$A17,'Dataset 1'!$J$7:$J$2506,G$5) -> 6840 | H17: =SUMIFS('Dataset 1'!$E$7:$E$2506,'Dataset 1'!$B$7:$B$2506,$A17,'Dataset 1'!$J$7:$J$2506,H$5) -> 0 | I17: =SUMIFS('Dataset 1'!$E$7:$E$2506,'Dataset 1'!$B$7:$B$2506,$A17,'Dataset 1'!$J$7:$J$2506,I$5) -> 0 | ... EG17: =SUMIFS('Dataset 1'!$E$7:$E$2506,'Dataset 1'!$B$7:$B$2506,$A17,'Dataset 1'!$J$7:$J$2506,EG$5) -> 0
... A26: 2025 | B26: =SUMIFS('Dataset 1'!$E$7:$E$2506,'Dataset 1'!$B$7:$B$2506,$A26,'Dataset 1'!$J$7:$J$2506,B$5) -> 0 | C26: =SUMIFS('Dataset 1'!$E$7:$E$2506,'Dataset 1'!$B$7:$B$2506,$A26,'Dataset 1'!$J$7:$J$2506,C$5) -> 530 | D26: =SUMIFS('Dataset 1'!$E$7:$E$2506,'Dataset 1'!$B$7:$B$2506,$A26,'Dataset 1'!$J$7:$J$2506,D$5) -> 0 | E26: =SUMIFS('Dataset 1'!$E$7:$E$2506,'Dataset 1'!$B$7:$B$2506,$A26,'Dataset 1'!$J$7:$J$2506,E$5) -> 0 | F26: =SUMIFS('Dataset 1'!$E$7:$E$2506,'Dataset 1'!$B$7:$B$2506,$A26,'Dataset 1'!$J$7:$J$2506,F$5) -> 380 | G26: =SUMIFS('Dataset 1'!$E$7:$E$2506,'Dataset 1'!$B$7:$B$2506,$A26,'Dataset 1'!$J$7:$J$2506,G$5) -> 680 | H26: =SUMIFS('Dataset 1'!$E$7:$E$2506,'Dataset 1'!$B$7:$B$2506,$A26,'Dataset 1'!$J$7:$J$2506,H$5) -> 0 | I26: =SUMIFS('Dataset 1'!$E$7:$E$2506,'Dataset 1'!$B$7:$B$2506,$A26,'Dataset 1'!$J$7:$J$2506,I$5) -> 0 | ... EG26: =SUMIFS('Dataset 1'!$E$7:$E$2506,'Dataset 1'!$B$7:$B$2506,$A26,'Dataset 1'!$J$7:$J$2506,EG$5) -> 360
A28: Cumulative stock proxy (USD millions) | B28: Afghanistan | C28: Algeria | D28: Angola | E28: Antigua and Barbuda | F28: Argentina | G28: Australia | H28: Austria | I28: Azerbaijan | J28: Bahamas | K28: Bangladesh | L28: Belarus | M28: Belgium | N28: Bolivia | O28: Bosnia | P28: Botswana | Q28: Brazil | R28: Britain | S28: Brunei | T28: Bulgaria | U28: Cambodia | V28: Cameroon | W28: Canada | X28: Chad | Y28: Chile | Z28: Colombia | AA28: Congo | AB28: Croatia | AC28: Cuba | AD28: Cyprus | AE28: Czech Republic | AF28: Democratic Republic of the Congo | AG28: Denmark | AH28: Djibouti | AI28: Ecuador | AJ28: Egypt | AK28: Eritrea | AL28: Ethiopia | AM28: Finland | AN28: France | AO28: Gabon | AP28: Georgia | AQ28: Germany | AR28: Ghana | AS28: Greece | AT28: Guinea | AU28: Guinea-Bissau | AV28: Guyana | AW28: Hungary | AX28: India | AY28: Indonesia | AZ28: Iran | BA28: Iraq | BB28: Ireland | BC28: Israel | BD28: Italy | BE28: Ivory Coast | BF28: Jamaica | BG28: Japan | BH28: Jordan | BI28: Kazakhstan | BJ28: Kenya | BK28: Kuwait | BL28: Kyrgyzstan | BM28: Laos | BN28: Liberia | BO28: Luxembourg | BP28: Madagascar | BQ28: Malawi | BR28: Malaysia | BS28: Maldives | BT28: Mali | BU28: Malta | BV28: Mauritius | BW28: Mexico | BX28: Mongolia | BY28: Montenegro | BZ28: Morocco | CA28: Mozambique | CB28: Myanmar | CC28: Namibia | CD28: Nepal | CE28: Netherlands | CF28: New Zealand | CG28: Nicaragua | CH28: Niger | CI28: Nigeria | CJ28: North Korea | CK28: Norway | CL28: Oman | CM28: Pakistan | CN28: Panama | CO28: Papua New Guinea | CP28: Peru | CQ28: Philippines | CR28: Poland | CS28: Portugal | CT28: Qatar | CU28: Russian Federation | CV28: Rwanda | CW28: Samoa | CX28: Sao Tome | CY28: Saudi Arabia | CZ28: Serbia | DA28: Sierra Leone | DB28: Singapore | DC28: Slovakia | DD28: Slovenia | DE28: Solomon Islands | DF28: South Africa | DG28: South Korea | DH28: Spain | DI28: Sri Lanka | DJ28: Sudan | DK28: Suriname | DL28: Sweden | DM28: Switzerland | DN28: Syria | DO28: Taiwan | DP28: Tajikistan | DQ28: Tanzania | DR28: Thailand | DS28: Togo | DT28: Trinidad-Tobago | DU28: Tunisia | DV28: Turkey | DW28: Turkmenistan | DX28: UAE | DY28: USA | DZ28: Uganda | EA28: Ukraine | EB28: Uzbekistan | EC28: Venezuela | ED28: Vietnam | EE28: Yemen | EF28: Zambia | EG28: Zimbabwe
A29: 2005 | B29: =SUMIFS('Dataset 1'!$E$7:$E$2506,'Dataset 1'!$B$7:$B$2506,"<="&$A29,'Dataset 1'!$J$7:$J$2506,B$5) -> 0 | C29: =SUMIFS('Dataset 1'!$E$7:$E$2506,'Dataset 1'!$B$7:$B$2506,"<="&$A29,'Dataset 1'!$J$7:$J$2506,C$5) -> 0 | D29: =SUMIFS('Dataset 1'!$E$7:$E$2506,'Dataset 1'!$B$7:$B$2506,"<="&$A29,'Dataset 1'!$J$7:$J$2506,D$5) -> 0 | E29: =SUMIFS('Dataset 1'!$E$7:$E$2506,'Dataset 1'!$B$7:$B$2506,"<="&$A29,'Dataset 1'!$J$7:$J$2506,E$5) -> 0 | F29: =SUMIFS('Dataset 1'!$E$7:$E$2506,'Dataset 1'!$B$7:$B$2506,"<="&$A29,'Dataset 1'!$J$7:$J$2506,F$5) -> 0 | G29: =SUMIFS('Dataset 1'!$E$7:$E$2506,'Dataset 1'!$B$7:$B$2506,"<="&$A29,'Dataset 1'!$J$7:$J$2506,G$5) -> 320 | H29: =SUMIFS('Dataset 1'!$E$7:$E$2506,'Dataset 1'!$B$7:$B$2506,"<="&$A29,'Dataset 1'!$J$7:$J$2506,H$5) -> 0 | I29: =SUMIFS('Dataset 1'!$E$7:$E$2506,'Dataset 1'!$B$7:$B$2506,"<="&$A29,'Dataset 1'!$J$7:$J$2506,I$5) -> 0 | ... EG29: =SUMIFS('Dataset 1'!$E$7:$E$2506,'Dataset 1'!$B$7:$B$2506,"<="&$A29,'Dataset 1'!$J$7:$J$2506,EG$5) -> 0
A30: 2006 | B30: =SUMIFS('Dataset 1'!$E$7:$E$2506,'Dataset 1'!$B$7:$B$2506,"<="&$A30,'Dataset 1'!$J$7:$J$2506,B$5) -> 0 | C30: =SUMIFS('Dataset 1'!$E$7:$E$2506,'Dataset 1'!$B$7:$B$2506,"<="&$A30,'Dataset 1'!$J$7:$J$2506,C$5) -> 0 | D30: =SUMIFS('Dataset 1'!$E$7:$E$2506,'Dataset 1'!$B$7:$B$2506,"<="&$A30,'Dataset 1'!$J$7:$J$2506,D$5) -> 740 | E30: =SUMIFS('Dataset 1'!$E$7:$E$2506,'Dataset 1'!$B$7:$B$2506,"<="&$A30,'Dataset 1'!$J$7:$J$2506,E$5) -> 0 | F30: =SUMIFS('Dataset 1'!$E$7:$E$2506,'Dataset 1'!$B$7:$B$2506,"<="&$A30,'Dataset 1'!$J$7:$J$2506,F$5) -> 0 | G30: =SUMIFS('Dataset 1'!$E$7:$E$2506,'Dataset 1'!$B$7:$B$2506,"<="&$A30,'Dataset 1'!$J$7:$J$2506,G$5) -> 3240 | H30: =SUMIFS('Dataset 1'!$E$7:$E$2506,'Dataset 1'!$B$7:$B$2506,"<="&$A30,'Dataset 1'!$J$7:$J$2506,H$5) -> 0 | I30: =SUMIFS('Dataset 1'!$E$7:$E$2506,'Dataset 1'!$B$7:$B$2506,"<="&$A30,'Dataset 1'!$J$7:$J$2506,I$5) -> 0 | ... EG30: =SUMIFS('Dataset 1'!$E$7:$E$2506,'Dataset 1'!$B$7:$B$2506,"<="&$A30,'Dataset 1'!$J$7:$J$2506,EG$5) -> 0
A31: 2007 | B31: =SUMIFS('Dataset 1'!$E$7:$E$2506,'Dataset 1'!$B$7:$B$2506,"<="&$A31,'Dataset 1'!$J$7:$J$2506,B$5) -> 2520 | C31: =SUMIFS('Dataset 1'!$E$7:$E$2506,'Dataset 1'!$B$7:$B$2506,"<="&$A31,'Dataset 1'!$J$7:$J$2506,C$5) -> 0 | D31: =SUMIFS('Dataset 1'!$E$7:$E$2506,'Dataset 1'!$B$7:$B$2506,"<="&$A31,'Dataset 1'!$J$7:$J$2506,D$5) -> 740 | E31: =SUMIFS('Dataset 1'!$E$7:$E$2506,'Dataset 1'!$B$7:$B$2506,"<="&$A31,'Dataset 1'!$J$7:$J$2506,E$5) -> 0 | F31: =SUMIFS('Dataset 1'!$E$7:$E$2506,'Dataset 1'!$B$7:$B$2506,"<="&$A31,'Dataset 1'!$J$7:$J$2506,F$5) -> 0 | G31: =SUMIFS('Dataset 1'!$E$7:$E$2506,'Dataset 1'!$B$7:$B$2506,"<="&$A31,'Dataset 1'!$J$7:$J$2506,G$5) -> 3670 | H31: =SUMIFS('Dataset 1'!$E$7:$E$2506,'Dataset 1'!$B$7:$B$2506,"<="&$A31,'Dataset 1'!$J$7:$J$2506,H$5) -> 0 | I31: =SUMIFS('Dataset 1'!$E$7:$E$2506,'Dataset 1'!$B$7:$B$2506,"<="&$A31,'Dataset 1'!$J$7:$J$2506,I$5) -> 0 | ... EG31: =SUMIFS('Dataset 1'!$E$7:$E$2506,'Dataset 1'!$B$7:$B$2506,"<="&$A31,'Dataset 1'!$J$7:$J$2506,EG$5) -> 100
A32: 2008 | B32: =SUMIFS('Dataset 1'!$E$7:$E$2506,'Dataset 1'!$B$7:$B$2506,"<="&$A32,'Dataset 1'!$J$7:$J$2506,B$5) -> 2520 | C32: =SUMIFS('Dataset 1'!$E$7:$E$2506,'Dataset 1'!$B$7:$B$2506,"<="&$A32,'Dataset 1'!$J$7:$J$2506,C$5) -> 0 | D32: =SUMIFS('Dataset 1'!$E$7:$E$2506,'Dataset 1'!$B$7:$B$2506,"<="&$A32,'Dataset 1'!$J$7:$J$2506,D$5) -> 740 | E32: =SUMIFS('Dataset 1'!$E$7:$E$2506,'Dataset 1'!$B$7:$B$2506,"<="&$A32,'Dataset 1'!$J$7:$J$2506,E$5) -> 0 | F32: =SUMIFS('Dataset 1'!$E$7:$E$2506,'Dataset 1'!$B$7:$B$2506,"<="&$A32,'Dataset 1'!$J$7:$J$2506,F$5) -> 0 | G32: =SUMIFS('Dataset 1'!$E$7:$E$2506,'Dataset 1'!$B$7:$B$2506,"<="&$A32,'Dataset 1'!$J$7:$J$2506,G$5) -> 19920 | H32: =SUMIFS('Dataset 1'!$E$7:$E$2506,'Dataset 1'!$B$7:$B$2506,"<="&$A32,'Dataset 1'!$J$7:$J$2506,H$5) -> 0 | I32: =SUMIFS('Dataset 1'!$E$7:$E$2506,'Dataset 1'!$B$7:$B$2506,"<="&$A32,'Dataset 1'!$J$7:$J$2506,I$5) -> 0 | ... EG32: =SUMIFS('Dataset 1'!$E$7:$E$2506,'Dataset 1'!$B$7:$B$2506,"<="&$A32,'Dataset 1'!$J$7:$J$2506,EG$5) -> 100
A33: 2009 | B33: =SUMIFS('Dataset 1'!$E$7:$E$2506,'Dataset 1'!$B$7:$B$2506,"<="&$A33,'Dataset 1'!$J$7:$J$2506,B$5) -> 2520 | C33: =SUMIFS('Dataset 1'!$E$7:$E$2506,'Dataset 1'!$B$7:$B$2506,"<="&$A33,'Dataset 1'!$J$7:$J$2506,C$5) -> 0 | D33: =SUMIFS('Dataset 1'!$E$7:$E$2506,'Dataset 1'!$B$7:$B$2506,"<="&$A33,'Dataset 1'!$J$7:$J$2506,D$5) -> 740 | E33: =SUMIFS('Dataset 1'!$E$7:$E$2506,'Dataset 1'!$B$7:$B$2506,"<="&$A33,'Dataset 1'!$J$7:$J$2506,E$5) -> 0 | F33: =SUMIFS('Dataset 1'!$E$7:$E$2506,'Dataset 1'!$B$7:$B$2506,"<="&$A33,'Dataset 1'!$J$7:$J$2506,F$5) -> 0 | G33: =SUMIFS('Dataset 1'!$E$7:$E$2506,'Dataset 1'!$B$7:$B$2506,"<="&$A33,'Dataset 1'!$J$7:$J$2506,G$5) -> 29050 | H33: =SUMIFS('Dataset 1'!$E$7:$E$2506,'Dataset 1'!$B$7:$B$2506,"<="&$A33,'Dataset 1'!$J$7:$J$2506,H$5) -> 140 | I33: =SUMIFS('Dataset 1'!$E$7:$E$2506,'Dataset 1'!$B$7:$B$2506,"<="&$A33,'Dataset 1'!$J$7:$J$2506,I$5) -> 0 | ... EG33: =SUMIFS('Dataset 1'!$E$7:$E$2506,'Dataset 1'!$B$7:$B$2506,"<="&$A33,'Dataset 1'!$J$7:$J$2506,EG$5) -> 100
A34: 2010 | B34: =SUMIFS('Dataset 1'!$E$7:$E$2506,'Dataset 1'!$B$7:$B$2506,"<="&$A34,'Dataset 1'!$J$7:$J$2506,B$5) -> 2520 | C34: =SUMIFS('Dataset 1'!$E$7:$E$2506,'Dataset 1'!$B$7:$B$2506,"<="&$A34,'Dataset 1'!$J$7:$J$2506,C$5) -> 0 | D34: =SUMIFS('Dataset 1'!$E$7:$E$2506,'Dataset 1'!$B$7:$B$2506,"<="&$A34,'Dataset 1'!$J$7:$J$2506,D$5) -> 740 | E34: =SUMIFS('Dataset 1'!$E$7:$E$2506,'Dataset 1'!$B$7:$B$2506,"<="&$A34,'Dataset 1'!$J$7:$J$2506,E$5) -> 0 | F34: =SUMIFS('Dataset 1'!$E$7:$E$2506,'Dataset 1'!$B$7:$B$2506,"<="&$A34,'Dataset 1'!$J$7:$J$2506,F$5) -> 5680 | G34: =SUMIFS('Dataset 1'!$E$7:$E$2506,'Dataset 1'!$B$7:$B$2506,"<="&$A34,'Dataset 1'!$J$7:$J$2506,G$5) -> 32390 | H34: =SUMIFS('Dataset 1'!$E$7:$E$2506,'Dataset 1'!$B$7:$B$2506,"<="&$A34,'Dataset 1'!$J$7:$J$2506,H$5) -> 140 | I34: =SUMIFS('Dataset 1'!$E$7:$E$2506,'Dataset 1'!$B$7:$B$2506,"<="&$A34,'Dataset 1'!$J$7:$J$2506,I$5) -> 0 | ... EG34: =SUMIFS('Dataset 1'!$E$7:$E$2506,'Dataset 1'!$B$7:$B$2506,"<="&$A34,'Dataset 1'!$J$7:$J$2506,EG$5) -> 100
A35: 2011 | B35: =SUMIFS('Dataset 1'!$E$7:$E$2506,'Dataset 1'!$B$7:$B$2506,"<="&$A35,'Dataset 1'!$J$7:$J$2506,B$5) -> 2920 | C35: =SUMIFS('Dataset 1'!$E$7:$E$2506,'Dataset 1'!$B$7:$B$2506,"<="&$A35,'Dataset 1'!$J$7:$J$2506,C$5) -> 0 | D35: =SUMIFS('Dataset 1'!$E$7:$E$2506,'Dataset 1'!$B$7:$B$2506,"<="&$A35,'Dataset 1'!$J$7:$J$2506,D$5) -> 2910 | E35: =SUMIFS('Dataset 1'!$E$7:$E$2506,'Dataset 1'!$B$7:$B$2506,"<="&$A35,'Dataset 1'!$J$7:$J$2506,E$5) -> 0 | F35: =SUMIFS('Dataset 1'!$E$7:$E$2506,'Dataset 1'!$B$7:$B$2506,"<="&$A35,'Dataset 1'!$J$7:$J$2506,F$5) -> 6960 | G35: =SUMIFS('Dataset 1'!$E$7:$E$2506,'Dataset 1'!$B$7:$B$2506,"<="&$A35,'Dataset 1'!$J$7:$J$2506,G$5) -> 42270 | H35: =SUMIFS('Dataset 1'!$E$7:$E$2506,'Dataset 1'!$B$7:$B$2506,"<="&$A35,'Dataset 1'!$J$7:$J$2506,H$5) -> 280 | I35: =SUMIFS('Dataset 1'!$E$7:$E$2506,'Dataset 1'!$B$7:$B$2506,"<="&$A35,'Dataset 1'!$J$7:$J$2506,I$5) -> 0 | ... EG35: =SUMIFS('Dataset 1'!$E$7:$E$2506,'Dataset 1'!$B$7:$B$2506,"<="&$A35,'Dataset 1'!$J$7:$J$2506,EG$5) -> 600
A36: 2012 | B36: =SUMIFS('Dataset 1'!$E$7:$E$2506,'Dataset 1'!$B$7:$B$2506,"<="&$A36,'Dataset 1'!$J$7:$J$2506,B$5) -> 2920 | C36: =SUMIFS('Dataset 1'!$E$7:$E$2506,'Dataset 1'!$B$7:$B$2506,"<="&$A36,'Dataset 1'!$J$7:$J$2506,C$5) -> 0 | D36: =SUMIFS('Dataset 1'!$E$7:$E$2506,'Dataset 1'!$B$7:$B$2506,"<="&$A36,'Dataset 1'!$J$7:$J$2506,D$5) -> 2910 | E36: =SUMIFS('Dataset 1'!$E$7:$E$2506,'Dataset 1'!$B$7:$B$2506,"<="&$A36,'Dataset 1'!$J$7:$J$2506,E$5) -> 0 | F36: =SUMIFS('Dataset 1'!$E$7:$E$2506,'Dataset 1'!$B$7:$B$2506,"<="&$A36,'Dataset 1'!$J$7:$J$2506,F$5) -> 6960 | G36: =SUMIFS('Dataset 1'!$E$7:$E$2506,'Dataset 1'!$B$7:$B$2506,"<="&$A36,'Dataset 1'!$J$7:$J$2506,G$5) -> 51350 | H36: =SUMIFS('Dataset 1'!$E$7:$E$2506,'Dataset 1'!$B$7:$B$2506,"<="&$A36,'Dataset 1'!$J$7:$J$2506,H$5) -> 280 | I36: =SUMIFS('Dataset 1'!$E$7:$E$2506,'Dataset 1'!$B$7:$B$2506,"<="&$A36,'Dataset 1'!$J$7:$J$2506,I$5) -> 0 | ... EG36: =SUMIFS('Dataset 1'!$E$7:$E$2506,'Dataset 1'!$B$7:$B$2506,"<="&$A36,'Dataset 1'!$J$7:$J$2506,EG$5) -> 600
A37: 2013 | B37: =SUMIFS('Dataset 1'!$E$7:$E$2506,'Dataset 1'!$B$7:$B$2506,"<="&$A37,'Dataset 1'!$J$7:$J$2506,B$5) -> 2920 | C37: =SUMIFS('Dataset 1'!$E$7:$E$2506,'Dataset 1'!$B$7:$B$2506,"<="&$A37,'Dataset 1'!$J$7:$J$2506,C$5) -> 0 | D37: =SUMIFS('Dataset 1'!$E$7:$E$2506,'Dataset 1'!$B$7:$B$2506,"<="&$A37,'Dataset 1'!$J$7:$J$2506,D$5) -> 5030 | E37: =SUMIFS('Dataset 1'!$E$7:$E$2506,'Dataset 1'!$B$7:$B$2506,"<="&$A37,'Dataset 1'!$J$7:$J$2506,E$5) -> 0 | F37: =SUMIFS('Dataset 1'!$E$7:$E$2506,'Dataset 1'!$B$7:$B$2506,"<="&$A37,'Dataset 1'!$J$7:$J$2506,F$5) -> 7080 | G37: =SUMIFS('Dataset 1'!$E$7:$E$2506,'Dataset 1'!$B$7:$B$2506,"<="&$A37,'Dataset 1'!$J$7:$J$2506,G$5) -> 60410 | H37: =SUMIFS('Dataset 1'!$E$7:$E$2506,'Dataset 1'!$B$7:$B$2506,"<="&$A37,'Dataset 1'!$J$7:$J$2506,H$5) -> 280 | I37: =SUMIFS('Dataset 1'!$E$7:$E$2506,'Dataset 1'!$B$7:$B$2506,"<="&$A37,'Dataset 1'!$J$7:$J$2506,I$5) -> 0 | ... EG37: =SUMIFS('Dataset 1'!$E$7:$E$2506,'Dataset 1'!$B$7:$B$2506,"<="&$A37,'Dataset 1'!$J$7:$J$2506,EG$5) -> 600
A38: 2014 | B38: =SUMIFS('Dataset 1'!$E$7:$E$2506,'Dataset 1'!$B$7:$B$2506,"<="&$A38,'Dataset 1'!$J$7:$J$2506,B$5) -> 2920 | C38: =SUMIFS('Dataset 1'!$E$7:$E$2506,'Dataset 1'!$B$7:$B$2506,"<="&$A38,'Dataset 1'!$J$7:$J$2506,C$5) -> 0 | D38: =SUMIFS('Dataset 1'!$E$7:$E$2506,'Dataset 1'!$B$7:$B$2506,"<="&$A38,'Dataset 1'!$J$7:$J$2506,D$5) -> 5150 | E38: =SUMIFS('Dataset 1'!$E$7:$E$2506,'Dataset 1'!$B$7:$B$2506,"<="&$A38,'Dataset 1'!$J$7:$J$2506,E$5) -> 740 | F38: =SUMIFS('Dataset 1'!$E$7:$E$2506,'Dataset 1'!$B$7:$B$2506,"<="&$A38,'Dataset 1'!$J$7:$J$2506,F$5) -> 7080 | G38: =SUMIFS('Dataset 1'!$E$7:$E$2506,'Dataset 1'!$B$7:$B$2506,"<="&$A38,'Dataset 1'!$J$7:$J$2506,G$5) -> 70470 | H38: =SUMIFS('Dataset 1'!$E$7:$E$2506,'Dataset 1'!$B$7:$B$2506,"<="&$A38,'Dataset 1'!$J$7:$J$2506,H$5) -> 280 | I38: =SUMIFS('Dataset 1'!$E$7:$E$2506,'Dataset 1'!$B$7:$B$2506,"<="&$A38,'Dataset 1'!$J$7:$J$2506,I$5) -> 0 | ... EG38: =SUMIFS('Dataset 1'!$E$7:$E$2506,'Dataset 1'!$B$7:$B$2506,"<="&$A38,'Dataset 1'!$J$7:$J$2506,EG$5) -> 850
A39: 2015 | B39: =SUMIFS('Dataset 1'!$E$7:$E$2506,'Dataset 1'!$B$7:$B$2506,"<="&$A39,'Dataset 1'!$J$7:$J$2506,B$5) -> 2920 | C39: =SUMIFS('Dataset 1'!$E$7:$E$2506,'Dataset 1'!$B$7:$B$2506,"<="&$A39,'Dataset 1'!$J$7:$J$2506,C$5) -> 0 | D39: =SUMIFS('Dataset 1'!$E$7:$E$2506,'Dataset 1'!$B$7:$B$2506,"<="&$A39,'Dataset 1'!$J$7:$J$2506,D$5) -> 5150 | E39: =SUMIFS('Dataset 1'!$E$7:$E$2506,'Dataset 1'!$B$7:$B$2506,"<="&$A39,'Dataset 1'!$J$7:$J$2506,E$5) -> 740 | F39: =SUMIFS('Dataset 1'!$E$7:$E$2506,'Dataset 1'!$B$7:$B$2506,"<="&$A39,'Dataset 1'!$J$7:$J$2506,F$5) -> 7380 | G39: =SUMIFS('Dataset 1'!$E$7:$E$2506,'Dataset 1'!$B$7:$B$2506,"<="&$A39,'Dataset 1'!$J$7:$J$2506,G$5) -> 81460 | H39: =SUMIFS('Dataset 1'!$E$7:$E$2506,'Dataset 1'!$B$7:$B$2506,"<="&$A39,'Dataset 1'!$J$7:$J$2506,H$5) -> 280 | I39: =SUMIFS('Dataset 1'!$E$7:$E$2506,'Dataset 1'!$B$7:$B$2506,"<="&$A39,'Dataset 1'!$J$7:$J$2506,I$5) -> 0 | ... EG39: =SUMIFS('Dataset 1'!$E$7:$E$2506,'Dataset 1'!$B$7:$B$2506,"<="&$A39,'Dataset 1'!$J$7:$J$2506,EG$5) -> 850
A40: 2016 | B40: =SUMIFS('Dataset 1'!$E$7:$E$2506,'Dataset 1'!$B$7:$B$2506,"<="&$A40,'Dataset 1'!$J$7:$J$2506,B$5) -> 2920 | C40: =SUMIFS('Dataset 1'!$E$7:$E$2506,'Dataset 1'!$B$7:$B$2506,"<="&$A40,'Dataset 1'!$J$7:$J$2506,C$5) -> 0 | D40: =SUMIFS('Dataset 1'!$E$7:$E$2506,'Dataset 1'!$B$7:$B$2506,"<="&$A40,'Dataset 1'!$J$7:$J$2506,D$5) -> 5150 | E40: =SUMIFS('Dataset 1'!$E$7:$E$2506,'Dataset 1'!$B$7:$B$2506,"<="&$A40,'Dataset 1'!$J$7:$J$2506,E$5) -> 740 | F40: =SUMIFS('Dataset 1'!$E$7:$E$2506,'Dataset 1'!$B$7:$B$2506,"<="&$A40,'Dataset 1'!$J$7:$J$2506,F$5) -> 7670 | G40: =SUMIFS('Dataset 1'!$E$7:$E$2506,'Dataset 1'!$B$7:$B$2506,"<="&$A40,'Dataset 1'!$J$7:$J$2506,G$5) -> 88300 | H40: =SUMIFS('Dataset 1'!$E$7:$E$2506,'Dataset 1'!$B$7:$B$2506,"<="&$A40,'Dataset 1'!$J$7:$J$2506,H$5) -> 280 | I40: =SUMIFS('Dataset 1'!$E$7:$E$2506,'Dataset 1'!$B$7:$B$2506,"<="&$A40,'Dataset 1'!$J$7:$J$2506,I$5) -> 0 | ... EG40: =SUMIFS('Dataset 1'!$E$7:$E$2506,'Dataset 1'!$B$7:$B$2506,"<="&$A40,'Dataset 1'!$J$7:$J$2506,EG$5) -> 850
... A49: 2025 | B49: =SUMIFS('Dataset 1'!$E$7:$E$2506,'Dataset 1'!$B$7:$B$2506,"<="&$A49,'Dataset 1'!$J$7:$J$2506,B$5) -> 3070 | C49: =SUMIFS('Dataset 1'!$E$7:$E$2506,'Dataset 1'!$B$7:$B$2506,"<="&$A49,'Dataset 1'!$J$7:$J$2506,C$5) -> 960 | D49: =SUMIFS('Dataset 1'!$E$7:$E$2506,'Dataset 1'!$B$7:$B$2506,"<="&$A49,'Dataset 1'!$J$7:$J$2506,D$5) -> 5520 | E49: =SUMIFS('Dataset 1'!$E$7:$E$2506,'Dataset 1'!$B$7:$B$2506,"<="&$A49,'Dataset 1'!$J$7:$J$2506,E$5) -> 740 | F49: =SUMIFS('Dataset 1'!$E$7:$E$2506,'Dataset 1'!$B$7:$B$2506,"<="&$A49,'Dataset 1'!$J$7:$J$2506,F$5) -> 13530 | G49: =SUMIFS('Dataset 1'!$E$7:$E$2506,'Dataset 1'!$B$7:$B$2506,"<="&$A49,'Dataset 1'!$J$7:$J$2506,G$5) -> 108180 | H49: =SUMIFS('Dataset 1'!$E$7:$E$2506,'Dataset 1'!$B$7:$B$2506,"<="&$A49,'Dataset 1'!$J$7:$J$2506,H$5) -> 1110 | I49: =SUMIFS('Dataset 1'!$E$7:$E$2506,'Dataset 1'!$B$7:$B$2506,"<="&$A49,'Dataset 1'!$J$7:$J$2506,I$5) -> 270 | ... EG49: =SUMIFS('Dataset 1'!$E$7:$E$2506,'Dataset 1'!$B$7:$B$2506,"<="&$A49,'Dataset 1'!$J$7:$J$2506,EG$5) -> 4710
A51: By investment sector
A52: Annual flow (USD millions) | B52: Agriculture | C52: Chemicals | D52: Energy | E52: Entertainment | F52: Finance | G52: Health | H52: Logistics | I52: Metals | J52: Other | K52: Real estate | L52: Technology | M52: Tourism | N52: Transport | O52: Utilities
A53: 2005 | B53: =SUMIFS('Dataset 1'!$E$7:$E$2506,'Dataset 1'!$B$7:$B$2506,$A53,'Dataset 1'!$H$7:$H$2506,B$52) -> 0 | C53: =SUMIFS('Dataset 1'!$E$7:$E$2506,'Dataset 1'!$B$7:$B$2506,$A53,'Dataset 1'!$H$7:$H$2506,C$52) -> 180 | D53: =SUMIFS('Dataset 1'!$E$7:$E$2506,'Dataset 1'!$B$7:$B$2506,$A53,'Dataset 1'!$H$7:$H$2506,D$52) -> 6640 | E53: =SUMIFS('Dataset 1'!$E$7:$E$2506,'Dataset 1'!$B$7:$B$2506,$A53,'Dataset 1'!$H$7:$H$2506,E$52) -> 0 | F53: =SUMIFS('Dataset 1'!$E$7:$E$2506,'Dataset 1'!$B$7:$B$2506,$A53,'Dataset 1'!$H$7:$H$2506,F$52) -> 0 | G53: =SUMIFS('Dataset 1'!$E$7:$E$2506,'Dataset 1'!$B$7:$B$2506,$A53,'Dataset 1'!$H$7:$H$2506,G$52) -> 0 | H53: =SUMIFS('Dataset 1'!$E$7:$E$2506,'Dataset 1'!$B$7:$B$2506,$A53,'Dataset 1'!$H$7:$H$2506,H$52) -> 0 | I53: =SUMIFS('Dataset 1'!$E$7:$E$2506,'Dataset 1'!$B$7:$B$2506,$A53,'Dataset 1'!$H$7:$H$2506,I$52) -> 1310 | ... O53: =SUMIFS('Dataset 1'!$E$7:$E$2506,'Dataset 1'!$B$7:$B$2506,$A53,'Dataset 1'!$H$7:$H$2506,O$52) -> 0
A54: 2006 | B54: =SUMIFS('Dataset 1'!$E$7:$E$2506,'Dataset 1'!$B$7:$B$2506,$A54,'Dataset 1'!$H$7:$H$2506,B$52) -> 480 | C54: =SUMIFS('Dataset 1'!$E$7:$E$2506,'Dataset 1'!$B$7:$B$2506,$A54,'Dataset 1'!$H$7:$H$2506,C$52) -> 0 | D54: =SUMIFS('Dataset 1'!$E$7:$E$2506,'Dataset 1'!$B$7:$B$2506,$A54,'Dataset 1'!$H$7:$H$2506,D$52) -> 10170 | E54: =SUMIFS('Dataset 1'!$E$7:$E$2506,'Dataset 1'!$B$7:$B$2506,$A54,'Dataset 1'!$H$7:$H$2506,E$52) -> 0 | F54: =SUMIFS('Dataset 1'!$E$7:$E$2506,'Dataset 1'!$B$7:$B$2506,$A54,'Dataset 1'!$H$7:$H$2506,F$52) -> 100 | G54: =SUMIFS('Dataset 1'!$E$7:$E$2506,'Dataset 1'!$B$7:$B$2506,$A54,'Dataset 1'!$H$7:$H$2506,G$52) -> 0 | H54: =SUMIFS('Dataset 1'!$E$7:$E$2506,'Dataset 1'!$B$7:$B$2506,$A54,'Dataset 1'!$H$7:$H$2506,H$52) -> 0 | I54: =SUMIFS('Dataset 1'!$E$7:$E$2506,'Dataset 1'!$B$7:$B$2506,$A54,'Dataset 1'!$H$7:$H$2506,I$52) -> 6470 | ... O54: =SUMIFS('Dataset 1'!$E$7:$E$2506,'Dataset 1'!$B$7:$B$2506,$A54,'Dataset 1'!$H$7:$H$2506,O$52) -> 0
A55: 2007 | B55: =SUMIFS('Dataset 1'!$E$7:$E$2506,'Dataset 1'!$B$7:$B$2506,$A55,'Dataset 1'!$H$7:$H$2506,B$52) -> 0 | C55: =SUMIFS('Dataset 1'!$E$7:$E$2506,'Dataset 1'!$B$7:$B$2506,$A55,'Dataset 1'!$H$7:$H$2506,C$52) -> 700 | D55: =SUMIFS('Dataset 1'!$E$7:$E$2506,'Dataset 1'!$B$7:$B$2506,$A55,'Dataset 1'!$H$7:$H$2506,D$52) -> 3200 | E55: =SUMIFS('Dataset 1'!$E$7:$E$2506,'Dataset 1'!$B$7:$B$2506,$A55,'Dataset 1'!$H$7:$H$2506,E$52) -> 0 | F55: =SUMIFS('Dataset 1'!$E$7:$E$2506,'Dataset 1'!$B$7:$B$2506,$A55,'Dataset 1'!$H$7:$H$2506,F$52) -> 19460 | G55: =SUMIFS('Dataset 1'!$E$7:$E$2506,'Dataset 1'!$B$7:$B$2506,$A55,'Dataset 1'!$H$7:$H$2506,G$52) -> 0 | H55: =SUMIFS('Dataset 1'!$E$7:$E$2506,'Dataset 1'!$B$7:$B$2506,$A55,'Dataset 1'!$H$7:$H$2506,H$52) -> 150 | I55: =SUMIFS('Dataset 1'!$E$7:$E$2506,'Dataset 1'!$B$7:$B$2506,$A55,'Dataset 1'!$H$7:$H$2506,I$52) -> 5930 | ... O55: =SUMIFS('Dataset 1'!$E$7:$E$2506,'Dataset 1'!$B$7:$B$2506,$A55,'Dataset 1'!$H$7:$H$2506,O$52) -> 0
A56: 2008 | B56: =SUMIFS('Dataset 1'!$E$7:$E$2506,'Dataset 1'!$B$7:$B$2506,$A56,'Dataset 1'!$H$7:$H$2506,B$52) -> 340 | C56: =SUMIFS('Dataset 1'!$E$7:$E$2506,'Dataset 1'!$B$7:$B$2506,$A56,'Dataset 1'!$H$7:$H$2506,C$52) -> 0 | D56: =SUMIFS('Dataset 1'!$E$7:$E$2506,'Dataset 1'!$B$7:$B$2506,$A56,'Dataset 1'!$H$7:$H$2506,D$52) -> 15530 | E56: =SUMIFS('Dataset 1'!$E$7:$E$2506,'Dataset 1'!$B$7:$B$2506,$A56,'Dataset 1'!$H$7:$H$2506,E$52) -> 0 | F56: =SUMIFS('Dataset 1'!$E$7:$E$2506,'Dataset 1'!$B$7:$B$2506,$A56,'Dataset 1'!$H$7:$H$2506,F$52) -> 4650 | G56: =SUMIFS('Dataset 1'!$E$7:$E$2506,'Dataset 1'!$B$7:$B$2506,$A56,'Dataset 1'!$H$7:$H$2506,G$52) -> 360 | H56: =SUMIFS('Dataset 1'!$E$7:$E$2506,'Dataset 1'!$B$7:$B$2506,$A56,'Dataset 1'!$H$7:$H$2506,H$52) -> 0 | I56: =SUMIFS('Dataset 1'!$E$7:$E$2506,'Dataset 1'!$B$7:$B$2506,$A56,'Dataset 1'!$H$7:$H$2506,I$52) -> 22800 | ... O56: =SUMIFS('Dataset 1'!$E$7:$E$2506,'Dataset 1'!$B$7:$B$2506,$A56,'Dataset 1'!$H$7:$H$2506,O$52) -> 3040
A57: 2009 | B57: =SUMIFS('Dataset 1'!$E$7:$E$2506,'Dataset 1'!$B$7:$B$2506,$A57,'Dataset 1'!$H$7:$H$2506,B$52) -> 370 | C57: =SUMIFS('Dataset 1'!$E$7:$E$2506,'Dataset 1'!$B$7:$B$2506,$A57,'Dataset 1'!$H$7:$H$2506,C$52) -> 0 | D57: =SUMIFS('Dataset 1'!$E$7:$E$2506,'Dataset 1'!$B$7:$B$2506,$A57,'Dataset 1'!$H$7:$H$2506,D$52) -> 35670 | E57: =SUMIFS('Dataset 1'!$E$7:$E$2506,'Dataset 1'!$B$7:$B$2506,$A57,'Dataset 1'!$H$7:$H$2506,E$52) -> 0 | F57: =SUMIFS('Dataset 1'!$E$7:$E$2506,'Dataset 1'!$B$7:$B$2506,$A57,'Dataset 1'!$H$7:$H$2506,F$52) -> 3100 | G57: =SUMIFS('Dataset 1'!$E$7:$E$2506,'Dataset 1'!$B$7:$B$2506,$A57,'Dataset 1'!$H$7:$H$2506,G$52) -> 0 | H57: =SUMIFS('Dataset 1'!$E$7:$E$2506,'Dataset 1'!$B$7:$B$2506,$A57,'Dataset 1'!$H$7:$H$2506,H$52) -> 0 | I57: =SUMIFS('Dataset 1'!$E$7:$E$2506,'Dataset 1'!$B$7:$B$2506,$A57,'Dataset 1'!$H$7:$H$2506,I$52) -> 10300 | ... O57: =SUMIFS('Dataset 1'!$E$7:$E$2506,'Dataset 1'!$B$7:$B$2506,$A57,'Dataset 1'!$H$7:$H$2506,O$52) -> 0
A58: 2010 | B58: =SUMIFS('Dataset 1'!$E$7:$E$2506,'Dataset 1'!$B$7:$B$2506,$A58,'Dataset 1'!$H$7:$H$2506,B$52) -> 1580 | C58: =SUMIFS('Dataset 1'!$E$7:$E$2506,'Dataset 1'!$B$7:$B$2506,$A58,'Dataset 1'!$H$7:$H$2506,C$52) -> 300 | D58: =SUMIFS('Dataset 1'!$E$7:$E$2506,'Dataset 1'!$B$7:$B$2506,$A58,'Dataset 1'!$H$7:$H$2506,D$52) -> 41190 | E58: =SUMIFS('Dataset 1'!$E$7:$E$2506,'Dataset 1'!$B$7:$B$2506,$A58,'Dataset 1'!$H$7:$H$2506,E$52) -> 100 | F58: =SUMIFS('Dataset 1'!$E$7:$E$2506,'Dataset 1'!$B$7:$B$2506,$A58,'Dataset 1'!$H$7:$H$2506,F$52) -> 3030 | G58: =SUMIFS('Dataset 1'!$E$7:$E$2506,'Dataset 1'!$B$7:$B$2506,$A58,'Dataset 1'!$H$7:$H$2506,G$52) -> 270 | H58: =SUMIFS('Dataset 1'!$E$7:$E$2506,'Dataset 1'!$B$7:$B$2506,$A58,'Dataset 1'!$H$7:$H$2506,H$52) -> 250 | I58: =SUMIFS('Dataset 1'!$E$7:$E$2506,'Dataset 1'!$B$7:$B$2506,$A58,'Dataset 1'!$H$7:$H$2506,I$52) -> 8910 | ... O58: =SUMIFS('Dataset 1'!$E$7:$E$2506,'Dataset 1'!$B$7:$B$2506,$A58,'Dataset 1'!$H$7:$H$2506,O$52) -> 0
A59: 2011 | B59: =SUMIFS('Dataset 1'!$E$7:$E$2506,'Dataset 1'!$B$7:$B$2506,$A59,'Dataset 1'!$H$7:$H$2506,B$52) -> 1610 | C59: =SUMIFS('Dataset 1'!$E$7:$E$2506,'Dataset 1'!$B$7:$B$2506,$A59,'Dataset 1'!$H$7:$H$2506,C$52) -> 4010 | D59: =SUMIFS('Dataset 1'!$E$7:$E$2506,'Dataset 1'!$B$7:$B$2506,$A59,'Dataset 1'!$H$7:$H$2506,D$52) -> 37660 | E59: =SUMIFS('Dataset 1'!$E$7:$E$2506,'Dataset 1'!$B$7:$B$2506,$A59,'Dataset 1'!$H$7:$H$2506,E$52) -> 400 | F59: =SUMIFS('Dataset 1'!$E$7:$E$2506,'Dataset 1'!$B$7:$B$2506,$A59,'Dataset 1'!$H$7:$H$2506,F$52) -> 2280 | G59: =SUMIFS('Dataset 1'!$E$7:$E$2506,'Dataset 1'!$B$7:$B$2506,$A59,'Dataset 1'!$H$7:$H$2506,G$52) -> 0 | H59: =SUMIFS('Dataset 1'!$E$7:$E$2506,'Dataset 1'!$B$7:$B$2506,$A59,'Dataset 1'!$H$7:$H$2506,H$52) -> 2340 | I59: =SUMIFS('Dataset 1'!$E$7:$E$2506,'Dataset 1'!$B$7:$B$2506,$A59,'Dataset 1'!$H$7:$H$2506,I$52) -> 11000 | ... O59: =SUMIFS('Dataset 1'!$E$7:$E$2506,'Dataset 1'!$B$7:$B$2506,$A59,'Dataset 1'!$H$7:$H$2506,O$52) -> 0
A60: 2012 | B60: =SUMIFS('Dataset 1'!$E$7:$E$2506,'Dataset 1'!$B$7:$B$2506,$A60,'Dataset 1'!$H$7:$H$2506,B$52) -> 3750 | C60: =SUMIFS('Dataset 1'!$E$7:$E$2506,'Dataset 1'!$B$7:$B$2506,$A60,'Dataset 1'!$H$7:$H$2506,C$52) -> 0 | D60: =SUMIFS('Dataset 1'!$E$7:$E$2506,'Dataset 1'!$B$7:$B$2506,$A60,'Dataset 1'!$H$7:$H$2506,D$52) -> 40390 | E60: =SUMIFS('Dataset 1'!$E$7:$E$2506,'Dataset 1'!$B$7:$B$2506,$A60,'Dataset 1'!$H$7:$H$2506,E$52) -> 3170 | F60: =SUMIFS('Dataset 1'!$E$7:$E$2506,'Dataset 1'!$B$7:$B$2506,$A60,'Dataset 1'!$H$7:$H$2506,F$52) -> 2900 | G60: =SUMIFS('Dataset 1'!$E$7:$E$2506,'Dataset 1'!$B$7:$B$2506,$A60,'Dataset 1'!$H$7:$H$2506,G$52) -> 1020 | H60: =SUMIFS('Dataset 1'!$E$7:$E$2506,'Dataset 1'!$B$7:$B$2506,$A60,'Dataset 1'!$H$7:$H$2506,H$52) -> 940 | I60: =SUMIFS('Dataset 1'!$E$7:$E$2506,'Dataset 1'!$B$7:$B$2506,$A60,'Dataset 1'!$H$7:$H$2506,I$52) -> 12670 | ... O60: =SUMIFS('Dataset 1'!$E$7:$E$2506,'Dataset 1'!$B$7:$B$2506,$A60,'Dataset 1'!$H$7:$H$2506,O$52) -> 1120
A61: 2013 | B61: =SUMIFS('Dataset 1'!$E$7:$E$2506,'Dataset 1'!$B$7:$B$2506,$A61,'Dataset 1'!$H$7:$H$2506,B$52) -> 9640 | C61: =SUMIFS('Dataset 1'!$E$7:$E$2506,'Dataset 1'!$B$7:$B$2506,$A61,'Dataset 1'!$H$7:$H$2506,C$52) -> 460 | D61: =SUMIFS('Dataset 1'!$E$7:$E$2506,'Dataset 1'!$B$7:$B$2506,$A61,'Dataset 1'!$H$7:$H$2506,D$52) -> 35760 | E61: =SUMIFS('Dataset 1'!$E$7:$E$2506,'Dataset 1'!$B$7:$B$2506,$A61,'Dataset 1'!$H$7:$H$2506,E$52) -> 350 | F61: =SUMIFS('Dataset 1'!$E$7:$E$2506,'Dataset 1'!$B$7:$B$2506,$A61,'Dataset 1'!$H$7:$H$2506,F$52) -> 1020 | G61: =SUMIFS('Dataset 1'!$E$7:$E$2506,'Dataset 1'!$B$7:$B$2506,$A61,'Dataset 1'!$H$7:$H$2506,G$52) -> 980 | H61: =SUMIFS('Dataset 1'!$E$7:$E$2506,'Dataset 1'!$B$7:$B$2506,$A61,'Dataset 1'!$H$7:$H$2506,H$52) -> 470 | I61: =SUMIFS('Dataset 1'!$E$7:$E$2506,'Dataset 1'!$B$7:$B$2506,$A61,'Dataset 1'!$H$7:$H$2506,I$52) -> 6180 | ... O61: =SUMIFS('Dataset 1'!$E$7:$E$2506,'Dataset 1'!$B$7:$B$2506,$A61,'Dataset 1'!$H$7:$H$2506,O$52) -> 100
A62: 2014 | B62: =SUMIFS('Dataset 1'!$E$7:$E$2506,'Dataset 1'!$B$7:$B$2506,$A62,'Dataset 1'!$H$7:$H$2506,B$52) -> 7650 | C62: =SUMIFS('Dataset 1'!$E$7:$E$2506,'Dataset 1'!$B$7:$B$2506,$A62,'Dataset 1'!$H$7:$H$2506,C$52) -> 0 | D62: =SUMIFS('Dataset 1'!$E$7:$E$2506,'Dataset 1'!$B$7:$B$2506,$A62,'Dataset 1'!$H$7:$H$2506,D$52) -> 29270 | E62: =SUMIFS('Dataset 1'!$E$7:$E$2506,'Dataset 1'!$B$7:$B$2506,$A62,'Dataset 1'!$H$7:$H$2506,E$52) -> 2110 | F62: =SUMIFS('Dataset 1'!$E$7:$E$2506,'Dataset 1'!$B$7:$B$2506,$A62,'Dataset 1'!$H$7:$H$2506,F$52) -> 5970 | G62: =SUMIFS('Dataset 1'!$E$7:$E$2506,'Dataset 1'!$B$7:$B$2506,$A62,'Dataset 1'!$H$7:$H$2506,G$52) -> 590 | H62: =SUMIFS('Dataset 1'!$E$7:$E$2506,'Dataset 1'!$B$7:$B$2506,$A62,'Dataset 1'!$H$7:$H$2506,H$52) -> 1370 | I62: =SUMIFS('Dataset 1'!$E$7:$E$2506,'Dataset 1'!$B$7:$B$2506,$A62,'Dataset 1'!$H$7:$H$2506,I$52) -> 14490 | ... O62: =SUMIFS('Dataset 1'!$E$7:$E$2506,'Dataset 1'!$B$7:$B$2506,$A62,'Dataset 1'!$H$7:$H$2506,O$52) -> 800
A63: 2015 | B63: =SUMIFS('Dataset 1'!$E$7:$E$2506,'Dataset 1'!$B$7:$B$2506,$A63,'Dataset 1'!$H$7:$H$2506,B$52) -> 1190 | C63: =SUMIFS('Dataset 1'!$E$7:$E$2506,'Dataset 1'!$B$7:$B$2506,$A63,'Dataset 1'!$H$7:$H$2506,C$52) -> 0 | D63: =SUMIFS('Dataset 1'!$E$7:$E$2506,'Dataset 1'!$B$7:$B$2506,$A63,'Dataset 1'!$H$7:$H$2506,D$52) -> 31400 | E63: =SUMIFS('Dataset 1'!$E$7:$E$2506,'Dataset 1'!$B$7:$B$2506,$A63,'Dataset 1'!$H$7:$H$2506,E$52) -> 3740 | F63: =SUMIFS('Dataset 1'!$E$7:$E$2506,'Dataset 1'!$B$7:$B$2506,$A63,'Dataset 1'!$H$7:$H$2506,F$52) -> 14040 | G63: =SUMIFS('Dataset 1'!$E$7:$E$2506,'Dataset 1'!$B$7:$B$2506,$A63,'Dataset 1'!$H$7:$H$2506,G$52) -> 2410 | H63: =SUMIFS('Dataset 1'!$E$7:$E$2506,'Dataset 1'!$B$7:$B$2506,$A63,'Dataset 1'!$H$7:$H$2506,H$52) -> 5430 | I63: =SUMIFS('Dataset 1'!$E$7:$E$2506,'Dataset 1'!$B$7:$B$2506,$A63,'Dataset 1'!$H$7:$H$2506,I$52) -> 5330 | ... O63: =SUMIFS('Dataset 1'!$E$7:$E$2506,'Dataset 1'!$B$7:$B$2506,$A63,'Dataset 1'!$H$7:$H$2506,O$52) -> 730
A64: 2016 | B64: =SUMIFS('Dataset 1'!$E$7:$E$2506,'Dataset 1'!$B$7:$B$2506,$A64,'Dataset 1'!$H$7:$H$2506,B$52) -> 6090 | C64: =SUMIFS('Dataset 1'!$E$7:$E$2506,'Dataset 1'!$B$7:$B$2506,$A64,'Dataset 1'!$H$7:$H$2506,C$52) -> 1650 | D64: =SUMIFS('Dataset 1'!$E$7:$E$2506,'Dataset 1'!$B$7:$B$2506,$A64,'Dataset 1'!$H$7:$H$2506,D$52) -> 37280 | E64: =SUMIFS('Dataset 1'!$E$7:$E$2506,'Dataset 1'!$B$7:$B$2506,$A64,'Dataset 1'!$H$7:$H$2506,E$52) -> 22030 | F64: =SUMIFS('Dataset 1'!$E$7:$E$2506,'Dataset 1'!$B$7:$B$2506,$A64,'Dataset 1'!$H$7:$H$2506,F$52) -> 3080 | G64: =SUMIFS('Dataset 1'!$E$7:$E$2506,'Dataset 1'!$B$7:$B$2506,$A64,'Dataset 1'!$H$7:$H$2506,G$52) -> 2820 | H64: =SUMIFS('Dataset 1'!$E$7:$E$2506,'Dataset 1'!$B$7:$B$2506,$A64,'Dataset 1'!$H$7:$H$2506,H$52) -> 3060 | I64: =SUMIFS('Dataset 1'!$E$7:$E$2506,'Dataset 1'!$B$7:$B$2506,$A64,'Dataset 1'!$H$7:$H$2506,I$52) -> 4600 | ... O64: =SUMIFS('Dataset 1'!$E$7:$E$2506,'Dataset 1'!$B$7:$B$2506,$A64,'Dataset 1'!$H$7:$H$2506,O$52) -> 1930
... A73: 2025 | B73: =SUMIFS('Dataset 1'!$E$7:$E$2506,'Dataset 1'!$B$7:$B$2506,$A73,'Dataset 1'!$H$7:$H$2506,B$52) -> 1070 | C73: =SUMIFS('Dataset 1'!$E$7:$E$2506,'Dataset 1'!$B$7:$B$2506,$A73,'Dataset 1'!$H$7:$H$2506,C$52) -> 1450 | D73: =SUMIFS('Dataset 1'!$E$7:$E$2506,'Dataset 1'!$B$7:$B$2506,$A73,'Dataset 1'!$H$7:$H$2506,D$52) -> 15890 | E73: =SUMIFS('Dataset 1'!$E$7:$E$2506,'Dataset 1'!$B$7:$B$2506,$A73,'Dataset 1'!$H$7:$H$2506,E$52) -> 2330 | F73: =SUMIFS('Dataset 1'!$E$7:$E$2506,'Dataset 1'!$B$7:$B$2506,$A73,'Dataset 1'!$H$7:$H$2506,F$52) -> 0 | G73: =SUMIFS('Dataset 1'!$E$7:$E$2506,'Dataset 1'!$B$7:$B$2506,$A73,'Dataset 1'!$H$7:$H$2506,G$52) -> 220 | H73: =SUMIFS('Dataset 1'!$E$7:$E$2506,'Dataset 1'!$B$7:$B$2506,$A73,'Dataset 1'!$H$7:$H$2506,H$52) -> 610 | I73: =SUMIFS('Dataset 1'!$E$7:$E$2506,'Dataset 1'!$B$7:$B$2506,$A73,'Dataset 1'!$H$7:$H$2506,I$52) -> 12810 | ... O73: =SUMIFS('Dataset 1'!$E$7:$E$2506,'Dataset 1'!$B$7:$B$2506,$A73,'Dataset 1'!$H$7:$H$2506,O$52) -> 310
A75: Cumulative stock proxy (USD millions) | B75: Agriculture | C75: Chemicals | D75: Energy | E75: Entertainment | F75: Finance | G75: Health | H75: Logistics | I75: Metals | J75: Other | K75: Real estate | L75: Technology | M75: Tourism | N75: Transport | O75: Utilities
A76: 2005 | B76: =SUMIFS('Dataset 1'!$E$7:$E$2506,'Dataset 1'!$B$7:$B$2506,"<="&$A76,'Dataset 1'!$H$7:$H$2506,B$52) -> 0 | C76: =SUMIFS('Dataset 1'!$E$7:$E$2506,'Dataset 1'!$B$7:$B$2506,"<="&$A76,'Dataset 1'!$H$7:$H$2506,C$52) -> 180 | D76: =SUMIFS('Dataset 1'!$E$7:$E$2506,'Dataset 1'!$B$7:$B$2506,"<="&$A76,'Dataset 1'!$H$7:$H$2506,D$52) -> 6640 | E76: =SUMIFS('Dataset 1'!$E$7:$E$2506,'Dataset 1'!$B$7:$B$2506,"<="&$A76,'Dataset 1'!$H$7:$H$2506,E$52) -> 0 | F76: =SUMIFS('Dataset 1'!$E$7:$E$2506,'Dataset 1'!$B$7:$B$2506,"<="&$A76,'Dataset 1'!$H$7:$H$2506,F$52) -> 0 | G76: =SUMIFS('Dataset 1'!$E$7:$E$2506,'Dataset 1'!$B$7:$B$2506,"<="&$A76,'Dataset 1'!$H$7:$H$2506,G$52) -> 0 | H76: =SUMIFS('Dataset 1'!$E$7:$E$2506,'Dataset 1'!$B$7:$B$2506,"<="&$A76,'Dataset 1'!$H$7:$H$2506,H$52) -> 0 | I76: =SUMIFS('Dataset 1'!$E$7:$E$2506,'Dataset 1'!$B$7:$B$2506,"<="&$A76,'Dataset 1'!$H$7:$H$2506,I$52) -> 1310 | ... O76: =SUMIFS('Dataset 1'!$E$7:$E$2506,'Dataset 1'!$B$7:$B$2506,"<="&$A76,'Dataset 1'!$H$7:$H$2506,O$52) -> 0
A77: 2006 | B77: =SUMIFS('Dataset 1'!$E$7:$E$2506,'Dataset 1'!$B$7:$B$2506,"<="&$A77,'Dataset 1'!$H$7:$H$2506,B$52) -> 480 | C77: =SUMIFS('Dataset 1'!$E$7:$E$2506,'Dataset 1'!$B$7:$B$2506,"<="&$A77,'Dataset 1'!$H$7:$H$2506,C$52) -> 180 | D77: =SUMIFS('Dataset 1'!$E$7:$E$2506,'Dataset 1'!$B$7:$B$2506,"<="&$A77,'Dataset 1'!$H$7:$H$2506,D$52) -> 16810 | E77: =SUMIFS('Dataset 1'!$E$7:$E$2506,'Dataset 1'!$B$7:$B$2506,"<="&$A77,'Dataset 1'!$H$7:$H$2506,E$52) -> 0 | F77: =SUMIFS('Dataset 1'!$E$7:$E$2506,'Dataset 1'!$B$7:$B$2506,"<="&$A77,'Dataset 1'!$H$7:$H$2506,F$52) -> 100 | G77: =SUMIFS('Dataset 1'!$E$7:$E$2506,'Dataset 1'!$B$7:$B$2506,"<="&$A77,'Dataset 1'!$H$7:$H$2506,G$52) -> 0 | H77: =SUMIFS('Dataset 1'!$E$7:$E$2506,'Dataset 1'!$B$7:$B$2506,"<="&$A77,'Dataset 1'!$H$7:$H$2506,H$52) -> 0 | I77: =SUMIFS('Dataset 1'!$E$7:$E$2506,'Dataset 1'!$B$7:$B$2506,"<="&$A77,'Dataset 1'!$H$7:$H$2506,I$52) -> 7780 | ... O77: =SUMIFS('Dataset 1'!$E$7:$E$2506,'Dataset 1'!$B$7:$B$2506,"<="&$A77,'Dataset 1'!$H$7:$H$2506,O$52) -> 0
A78: 2007 | B78: =SUMIFS('Dataset 1'!$E$7:$E$2506,'Dataset 1'!$B$7:$B$2506,"<="&$A78,'Dataset 1'!$H$7:$H$2506,B$52) -> 480 | C78: =SUMIFS('Dataset 1'!$E$7:$E$2506,'Dataset 1'!$B$7:$B$2506,"<="&$A78,'Dataset 1'!$H$7:$H$2506,C$52) -> 880 | D78: =SUMIFS('Dataset 1'!$E$7:$E$2506,'Dataset 1'!$B$7:$B$2506,"<="&$A78,'Dataset 1'!$H$7:$H$2506,D$52) -> 20010 | E78: =SUMIFS('Dataset 1'!$E$7:$E$2506,'Dataset 1'!$B$7:$B$2506,"<="&$A78,'Dataset 1'!$H$7:$H$2506,E$52) -> 0 | F78: =SUMIFS('Dataset 1'!$E$7:$E$2506,'Dataset 1'!$B$7:$B$2506,"<="&$A78,'Dataset 1'!$H$7:$H$2506,F$52) -> 19560 | G78: =SUMIFS('Dataset 1'!$E$7:$E$2506,'Dataset 1'!$B$7:$B$2506,"<="&$A78,'Dataset 1'!$H$7:$H$2506,G$52) -> 0 | H78: =SUMIFS('Dataset 1'!$E$7:$E$2506,'Dataset 1'!$B$7:$B$2506,"<="&$A78,'Dataset 1'!$H$7:$H$2506,H$52) -> 150 | I78: =SUMIFS('Dataset 1'!$E$7:$E$2506,'Dataset 1'!$B$7:$B$2506,"<="&$A78,'Dataset 1'!$H$7:$H$2506,I$52) -> 13710 | ... O78: =SUMIFS('Dataset 1'!$E$7:$E$2506,'Dataset 1'!$B$7:$B$2506,"<="&$A78,'Dataset 1'!$H$7:$H$2506,O$52) -> 0
A79: 2008 | B79: =SUMIFS('Dataset 1'!$E$7:$E$2506,'Dataset 1'!$B$7:$B$2506,"<="&$A79,'Dataset 1'!$H$7:$H$2506,B$52) -> 820 | C79: =SUMIFS('Dataset 1'!$E$7:$E$2506,'Dataset 1'!$B$7:$B$2506,"<="&$A79,'Dataset 1'!$H$7:$H$2506,C$52) -> 880 | D79: =SUMIFS('Dataset 1'!$E$7:$E$2506,'Dataset 1'!$B$7:$B$2506,"<="&$A79,'Dataset 1'!$H$7:$H$2506,D$52) -> 35540 | E79: =SUMIFS('Dataset 1'!$E$7:$E$2506,'Dataset 1'!$B$7:$B$2506,"<="&$A79,'Dataset 1'!$H$7:$H$2506,E$52) -> 0 | F79: =SUMIFS('Dataset 1'!$E$7:$E$2506,'Dataset 1'!$B$7:$B$2506,"<="&$A79,'Dataset 1'!$H$7:$H$2506,F$52) -> 24210 | G79: =SUMIFS('Dataset 1'!$E$7:$E$2506,'Dataset 1'!$B$7:$B$2506,"<="&$A79,'Dataset 1'!$H$7:$H$2506,G$52) -> 360 | H79: =SUMIFS('Dataset 1'!$E$7:$E$2506,'Dataset 1'!$B$7:$B$2506,"<="&$A79,'Dataset 1'!$H$7:$H$2506,H$52) -> 150 | I79: =SUMIFS('Dataset 1'!$E$7:$E$2506,'Dataset 1'!$B$7:$B$2506,"<="&$A79,'Dataset 1'!$H$7:$H$2506,I$52) -> 36510 | ... O79: =SUMIFS('Dataset 1'!$E$7:$E$2506,'Dataset 1'!$B$7:$B$2506,"<="&$A79,'Dataset 1'!$H$7:$H$2506,O$52) -> 3040
A80: 2009 | B80: =SUMIFS('Dataset 1'!$E$7:$E$2506,'Dataset 1'!$B$7:$B$2506,"<="&$A80,'Dataset 1'!$H$7:$H$2506,B$52) -> 1190 | C80: =SUMIFS('Dataset 1'!$E$7:$E$2506,'Dataset 1'!$B$7:$B$2506,"<="&$A80,'Dataset 1'!$H$7:$H$2506,C$52) -> 880 | D80: =SUMIFS('Dataset 1'!$E$7:$E$2506,'Dataset 1'!$B$7:$B$2506,"<="&$A80,'Dataset 1'!$H$7:$H$2506,D$52) -> 71210 | E80: =SUMIFS('Dataset 1'!$E$7:$E$2506,'Dataset 1'!$B$7:$B$2506,"<="&$A80,'Dataset 1'!$H$7:$H$2506,E$52) -> 0 | F80: =SUMIFS('Dataset 1'!$E$7:$E$2506,'Dataset 1'!$B$7:$B$2506,"<="&$A80,'Dataset 1'!$H$7:$H$2506,F$52) -> 27310 | G80: =SUMIFS('Dataset 1'!$E$7:$E$2506,'Dataset 1'!$B$7:$B$2506,"<="&$A80,'Dataset 1'!$H$7:$H$2506,G$52) -> 360 | H80: =SUMIFS('Dataset 1'!$E$7:$E$2506,'Dataset 1'!$B$7:$B$2506,"<="&$A80,'Dataset 1'!$H$7:$H$2506,H$52) -> 150 | I80: =SUMIFS('Dataset 1'!$E$7:$E$2506,'Dataset 1'!$B$7:$B$2506,"<="&$A80,'Dataset 1'!$H$7:$H$2506,I$52) -> 46810 | ... O80: =SUMIFS('Dataset 1'!$E$7:$E$2506,'Dataset 1'!$B$7:$B$2506,"<="&$A80,'Dataset 1'!$H$7:$H$2506,O$52) -> 3040
A81: 2010 | B81: =SUMIFS('Dataset 1'!$E$7:$E$2506,'Dataset 1'!$B$7:$B$2506,"<="&$A81,'Dataset 1'!$H$7:$H$2506,B$52) -> 2770 | C81: =SUMIFS('Dataset 1'!$E$7:$E$2506,'Dataset 1'!$B$7:$B$2506,"<="&$A81,'Dataset 1'!$H$7:$H$2506,C$52) -> 1180 | D81: =SUMIFS('Dataset 1'!$E$7:$E$2506,'Dataset 1'!$B$7:$B$2506,"<="&$A81,'Dataset 1'!$H$7:$H$2506,D$52) -> 112400 | E81: =SUMIFS('Dataset 1'!$E$7:$E$2506,'Dataset 1'!$B$7:$B$2506,"<="&$A81,'Dataset 1'!$H$7:$H$2506,E$52) -> 100 | F81: =SUMIFS('Dataset 1'!$E$7:$E$2506,'Dataset 1'!$B$7:$B$2506,"<="&$A81,'Dataset 1'!$H$7:$H$2506,F$52) -> 30340 | G81: =SUMIFS('Dataset 1'!$E$7:$E$2506,'Dataset 1'!$B$7:$B$2506,"<="&$A81,'Dataset 1'!$H$7:$H$2506,G$52) -> 630 | H81: =SUMIFS('Dataset 1'!$E$7:$E$2506,'Dataset 1'!$B$7:$B$2506,"<="&$A81,'Dataset 1'!$H$7:$H$2506,H$52) -> 400 | I81: =SUMIFS('Dataset 1'!$E$7:$E$2506,'Dataset 1'!$B$7:$B$2506,"<="&$A81,'Dataset 1'!$H$7:$H$2506,I$52) -> 55720 | ... O81: =SUMIFS('Dataset 1'!$E$7:$E$2506,'Dataset 1'!$B$7:$B$2506,"<="&$A81,'Dataset 1'!$H$7:$H$2506,O$52) -> 3040
A82: 2011 | B82: =SUMIFS('Dataset 1'!$E$7:$E$2506,'Dataset 1'!$B$7:$B$2506,"<="&$A82,'Dataset 1'!$H$7:$H$2506,B$52) -> 4380 | C82: =SUMIFS('Dataset 1'!$E$7:$E$2506,'Dataset 1'!$B$7:$B$2506,"<="&$A82,'Dataset 1'!$H$7:$H$2506,C$52) -> 5190 | D82: =SUMIFS('Dataset 1'!$E$7:$E$2506,'Dataset 1'!$B$7:$B$2506,"<="&$A82,'Dataset 1'!$H$7:$H$2506,D$52) -> 150060 | E82: =SUMIFS('Dataset 1'!$E$7:$E$2506,'Dataset 1'!$B$7:$B$2506,"<="&$A82,'Dataset 1'!$H$7:$H$2506,E$52) -> 500 | F82: =SUMIFS('Dataset 1'!$E$7:$E$2506,'Dataset 1'!$B$7:$B$2506,"<="&$A82,'Dataset 1'!$H$7:$H$2506,F$52) -> 32620 | G82: =SUMIFS('Dataset 1'!$E$7:$E$2506,'Dataset 1'!$B$7:$B$2506,"<="&$A82,'Dataset 1'!$H$7:$H$2506,G$52) -> 630 | H82: =SUMIFS('Dataset 1'!$E$7:$E$2506,'Dataset 1'!$B$7:$B$2506,"<="&$A82,'Dataset 1'!$H$7:$H$2506,H$52) -> 2740 | I82: =SUMIFS('Dataset 1'!$E$7:$E$2506,'Dataset 1'!$B$7:$B$2506,"<="&$A82,'Dataset 1'!$H$7:$H$2506,I$52) -> 66720 | ... O82: =SUMIFS('Dataset 1'!$E$7:$E$2506,'Dataset 1'!$B$7:$B$2506,"<="&$A82,'Dataset 1'!$H$7:$H$2506,O$52) -> 3040
A83: 2012 | B83: =SUMIFS('Dataset 1'!$E$7:$E$2506,'Dataset 1'!$B$7:$B$2506,"<="&$A83,'Dataset 1'!$H$7:$H$2506,B$52) -> 8130 | C83: =SUMIFS('Dataset 1'!$E$7:$E$2506,'Dataset 1'!$B$7:$B$2506,"<="&$A83,'Dataset 1'!$H$7:$H$2506,C$52) -> 5190 | D83: =SUMIFS('Dataset 1'!$E$7:$E$2506,'Dataset 1'!$B$7:$B$2506,"<="&$A83,'Dataset 1'!$H$7:$H$2506,D$52) -> 190450 | E83: =SUMIFS('Dataset 1'!$E$7:$E$2506,'Dataset 1'!$B$7:$B$2506,"<="&$A83,'Dataset 1'!$H$7:$H$2506,E$52) -> 3670 | F83: =SUMIFS('Dataset 1'!$E$7:$E$2506,'Dataset 1'!$B$7:$B$2506,"<="&$A83,'Dataset 1'!$H$7:$H$2506,F$52) -> 35520 | G83: =SUMIFS('Dataset 1'!$E$7:$E$2506,'Dataset 1'!$B$7:$B$2506,"<="&$A83,'Dataset 1'!$H$7:$H$2506,G$52) -> 1650 | H83: =SUMIFS('Dataset 1'!$E$7:$E$2506,'Dataset 1'!$B$7:$B$2506,"<="&$A83,'Dataset 1'!$H$7:$H$2506,H$52) -> 3680 | I83: =SUMIFS('Dataset 1'!$E$7:$E$2506,'Dataset 1'!$B$7:$B$2506,"<="&$A83,'Dataset 1'!$H$7:$H$2506,I$52) -> 79390 | ... O83: =SUMIFS('Dataset 1'!$E$7:$E$2506,'Dataset 1'!$B$7:$B$2506,"<="&$A83,'Dataset 1'!$H$7:$H$2506,O$52) -> 4160
A84: 2013 | B84: =SUMIFS('Dataset 1'!$E$7:$E$2506,'Dataset 1'!$B$7:$B$2506,"<="&$A84,'Dataset 1'!$H$7:$H$2506,B$52) -> 17770 | C84: =SUMIFS('Dataset 1'!$E$7:$E$2506,'Dataset 1'!$B$7:$B$2506,"<="&$A84,'Dataset 1'!$H$7:$H$2506,C$52) -> 5650 | D84: =SUMIFS('Dataset 1'!$E$7:$E$2506,'Dataset 1'!$B$7:$B$2506,"<="&$A84,'Dataset 1'!$H$7:$H$2506,D$52) -> 226210 | E84: =SUMIFS('Dataset 1'!$E$7:$E$2506,'Dataset 1'!$B$7:$B$2506,"<="&$A84,'Dataset 1'!$H$7:$H$2506,E$52) -> 4020 | F84: =SUMIFS('Dataset 1'!$E$7:$E$2506,'Dataset 1'!$B$7:$B$2506,"<="&$A84,'Dataset 1'!$H$7:$H$2506,F$52) -> 36540 | G84: =SUMIFS('Dataset 1'!$E$7:$E$2506,'Dataset 1'!$B$7:$B$2506,"<="&$A84,'Dataset 1'!$H$7:$H$2506,G$52) -> 2630 | H84: =SUMIFS('Dataset 1'!$E$7:$E$2506,'Dataset 1'!$B$7:$B$2506,"<="&$A84,'Dataset 1'!$H$7:$H$2506,H$52) -> 4150 | I84: =SUMIFS('Dataset 1'!$E$7:$E$2506,'Dataset 1'!$B$7:$B$2506,"<="&$A84,'Dataset 1'!$H$7:$H$2506,I$52) -> 85570 | ... O84: =SUMIFS('Dataset 1'!$E$7:$E$2506,'Dataset 1'!$B$7:$B$2506,"<="&$A84,'Dataset 1'!$H$7:$H$2506,O$52) -> 4260
A85: 2014 | B85: =SUMIFS('Dataset 1'!$E$7:$E$2506,'Dataset 1'!$B$7:$B$2506,"<="&$A85,'Dataset 1'!$H$7:$H$2506,B$52) -> 25420 | C85: =SUMIFS('Dataset 1'!$E$7:$E$2506,'Dataset 1'!$B$7:$B$2506,"<="&$A85,'Dataset 1'!$H$7:$H$2506,C$52) -> 5650 | D85: =SUMIFS('Dataset 1'!$E$7:$E$2506,'Dataset 1'!$B$7:$B$2506,"<="&$A85,'Dataset 1'!$H$7:$H$2506,D$52) -> 255480 | E85: =SUMIFS('Dataset 1'!$E$7:$E$2506,'Dataset 1'!$B$7:$B$2506,"<="&$A85,'Dataset 1'!$H$7:$H$2506,E$52) -> 6130 | F85: =SUMIFS('Dataset 1'!$E$7:$E$2506,'Dataset 1'!$B$7:$B$2506,"<="&$A85,'Dataset 1'!$H$7:$H$2506,F$52) -> 42510 | G85: =SUMIFS('Dataset 1'!$E$7:$E$2506,'Dataset 1'!$B$7:$B$2506,"<="&$A85,'Dataset 1'!$H$7:$H$2506,G$52) -> 3220 | H85: =SUMIFS('Dataset 1'!$E$7:$E$2506,'Dataset 1'!$B$7:$B$2506,"<="&$A85,'Dataset 1'!$H$7:$H$2506,H$52) -> 5520 | I85: =SUMIFS('Dataset 1'!$E$7:$E$2506,'Dataset 1'!$B$7:$B$2506,"<="&$A85,'Dataset 1'!$H$7:$H$2506,I$52) -> 100060 | ... O85: =SUMIFS('Dataset 1'!$E$7:$E$2506,'Dataset 1'!$B$7:$B$2506,"<="&$A85,'Dataset 1'!$H$7:$H$2506,O$52) -> 5060
A86: 2015 | B86: =SUMIFS('Dataset 1'!$E$7:$E$2506,'Dataset 1'!$B$7:$B$2506,"<="&$A86,'Dataset 1'!$H$7:$H$2506,B$52) -> 26610 | C86: =SUMIFS('Dataset 1'!$E$7:$E$2506,'Dataset 1'!$B$7:$B$2506,"<="&$A86,'Dataset 1'!$H$7:$H$2506,C$52) -> 5650 | D86: =SUMIFS('Dataset 1'!$E$7:$E$2506,'Dataset 1'!$B$7:$B$2506,"<="&$A86,'Dataset 1'!$H$7:$H$2506,D$52) -> 286880 | E86: =SUMIFS('Dataset 1'!$E$7:$E$2506,'Dataset 1'!$B$7:$B$2506,"<="&$A86,'Dataset 1'!$H$7:$H$2506,E$52) -> 9870 | F86: =SUMIFS('Dataset 1'!$E$7:$E$2506,'Dataset 1'!$B$7:$B$2506,"<="&$A86,'Dataset 1'!$H$7:$H$2506,F$52) -> 56550 | G86: =SUMIFS('Dataset 1'!$E$7:$E$2506,'Dataset 1'!$B$7:$B$2506,"<="&$A86,'Dataset 1'!$H$7:$H$2506,G$52) -> 5630 | H86: =SUMIFS('Dataset 1'!$E$7:$E$2506,'Dataset 1'!$B$7:$B$2506,"<="&$A86,'Dataset 1'!$H$7:$H$2506,H$52) -> 10950 | I86: =SUMIFS('Dataset 1'!$E$7:$E$2506,'Dataset 1'!$B$7:$B$2506,"<="&$A86,'Dataset 1'!$H$7:$H$2506,I$52) -> 105390 | ... O86: =SUMIFS('Dataset 1'!$E$7:$E$2506,'Dataset 1'!$B$7:$B$2506,"<="&$A86,'Dataset 1'!$H$7:$H$2506,O$52) -> 5790
A87: 2016 | B87: =SUMIFS('Dataset 1'!$E$7:$E$2506,'Dataset 1'!$B$7:$B$2506,"<="&$A87,'Dataset 1'!$H$7:$H$2506,B$52) -> 32700 | C87: =SUMIFS('Dataset 1'!$E$7:$E$2506,'Dataset 1'!$B$7:$B$2506,"<="&$A87,'Dataset 1'!$H$7:$H$2506,C$52) -> 7300 | D87: =SUMIFS('Dataset 1'!$E$7:$E$2506,'Dataset 1'!$B$7:$B$2506,"<="&$A87,'Dataset 1'!$H$7:$H$2506,D$52) -> 324160 | E87: =SUMIFS('Dataset 1'!$E$7:$E$2506,'Dataset 1'!$B$7:$B$2506,"<="&$A87,'Dataset 1'!$H$7:$H$2506,E$52) -> 31900 | F87: =SUMIFS('Dataset 1'!$E$7:$E$2506,'Dataset 1'!$B$7:$B$2506,"<="&$A87,'Dataset 1'!$H$7:$H$2506,F$52) -> 59630 | G87: =SUMIFS('Dataset 1'!$E$7:$E$2506,'Dataset 1'!$B$7:$B$2506,"<="&$A87,'Dataset 1'!$H$7:$H$2506,G$52) -> 8450 | H87: =SUMIFS('Dataset 1'!$E$7:$E$2506,'Dataset 1'!$B$7:$B$2506,"<="&$A87,'Dataset 1'!$H$7:$H$2506,H$52) -> 14010 | I87: =SUMIFS('Dataset 1'!$E$7:$E$2506,'Dataset 1'!$B$7:$B$2506,"<="&$A87,'Dataset 1'!$H$7:$H$2506,I$52) -> 109990 | ... O87: =SUMIFS('Dataset 1'!$E$7:$E$2506,'Dataset 1'!$B$7:$B$2506,"<="&$A87,'Dataset 1'!$H$7:$H$2506,O$52) -> 7720
... A96: 2025 | B96: =SUMIFS('Dataset 1'!$E$7:$E$2506,'Dataset 1'!$B$7:$B$2506,"<="&$A96,'Dataset 1'!$H$7:$H$2506,B$52) -> 88120 | C96: =SUMIFS('Dataset 1'!$E$7:$E$2506,'Dataset 1'!$B$7:$B$2506,"<="&$A96,'Dataset 1'!$H$7:$H$2506,C$52) -> 15810 | D96: =SUMIFS('Dataset 1'!$E$7:$E$2506,'Dataset 1'!$B$7:$B$2506,"<="&$A96,'Dataset 1'!$H$7:$H$2506,D$52) -> 485700 | E96: =SUMIFS('Dataset 1'!$E$7:$E$2506,'Dataset 1'!$B$7:$B$2506,"<="&$A96,'Dataset 1'!$H$7:$H$2506,E$52) -> 65600 | F96: =SUMIFS('Dataset 1'!$E$7:$E$2506,'Dataset 1'!$B$7:$B$2506,"<="&$A96,'Dataset 1'!$H$7:$H$2506,F$52) -> 89640 | G96: =SUMIFS('Dataset 1'!$E$7:$E$2506,'Dataset 1'!$B$7:$B$2506,"<="&$A96,'Dataset 1'!$H$7:$H$2506,G$52) -> 32080 | H96: =SUMIFS('Dataset 1'!$E$7:$E$2506,'Dataset 1'!$B$7:$B$2506,"<="&$A96,'Dataset 1'!$H$7:$H$2506,H$52) -> 46650 | I96: =SUMIFS('Dataset 1'!$E$7:$E$2506,'Dataset 1'!$B$7:$B$2506,"<="&$A96,'Dataset 1'!$H$7:$H$2506,I$52) -> 202780 | ... O96: =SUMIFS('Dataset 1'!$E$7:$E$2506,'Dataset 1'!$B$7:$B$2506,"<="&$A96,'Dataset 1'!$H$7:$H$2506,O$52) -> 10300
B130: 100% stacked area chart data | P130: 100% stacked area chart data
B131: USA | C131: Australia | D131: Britain | E131: Brazil | F131: Switzerland | G131: Canada | H131: Germany | I131: Indonesia | J131: Singapore | K131: France | L131: Other | P131: Energy | Q131: Transport | R131: Metals | S131: Real estate | T131: Finance | U131: Agriculture | V131: Technology | W131: Other | X131: Entertainment | Y131: Tourism | Z131: Other
A132: 2005 | B132: =DY29 -> 1740 | C132: =G29 -> 320 | D132: =R29 -> 100 | E132: =Q29 -> 0 | F132: =DM29 -> 0 | G132: =W29 -> 250 | H132: =AQ29 -> 0 | I132: =AY29 -> 0 | J132: =DB29 -> 0 | K132: =AN29 -> 0 | L132: =SUM($B29:$EG29)-SUM(B132:K132) -> 7710 | O132: 2005 | P132: =D76 -> 6640 | Q132: =N76 -> 100 | R132: =I76 -> 1310 | S132: =K76 -> 0 | T132: =F76 -> 0 | U132: =B76 -> 0 | V132: =L76 -> 1740 | W132: =J76 -> 150 | X132: =E76 -> 0 | Y132: =M76 -> 0 | Z132: =SUM($B76:$O76)-SUM(P132:Y132) -> 180
A133: 2006 | B133: =DY30 -> 1740 | C133: =G30 -> 3240 | D133: =R30 -> 900 | E133: =Q30 -> 0 | F133: =DM30 -> 0 | G133: =W30 -> 360 | H133: =AQ30 -> 0 | I133: =AY30 -> 100 | J133: =DB30 -> 970 | K133: =AN30 -> 480 | L133: =SUM($B30:$EG30)-SUM(B133:K133) -> 21940 | O133: 2006 | P133: =D77 -> 16810 | Q133: =N77 -> 1070 | R133: =I77 -> 7780 | S133: =K77 -> 1300 | T133: =F77 -> 100 | U133: =B77 -> 480 | V133: =L77 -> 1740 | W133: =J77 -> 270 | X133: =E77 -> 0 | Y133: =M77 -> 0 | Z133: =SUM($B77:$O77)-SUM(P133:Y133) -> 180
A134: 2007 | B134: =DY31 -> 10140 | C134: =G31 -> 3670 | D134: =R31 -> 3940 | E134: =Q31 -> 0 | F134: =DM31 -> 0 | G134: =W31 -> 360 | H134: =AQ31 -> 130 | I134: =AY31 -> 100 | J134: =DB31 -> 970 | K134: =AN31 -> 1180 | L134: =SUM($B31:$EG31)-SUM(B134:K134) -> 39680 | O134: 2007 | P134: =D78 -> 20010 | Q134: =N78 -> 1340 | R134: =I78 -> 13710 | S134: =K78 -> 1450 | T134: =F78 -> 19560 | U134: =B78 -> 480 | V134: =L78 -> 2200 | W134: =J78 -> 390 | X134: =E78 -> 0 | Y134: =M78 -> 0 | Z134: =SUM($B78:$O78)-SUM(P134:Y134) -> 1030
A135: 2008 | B135: =DY32 -> 15110 | C135: =G32 -> 19920 | D135: =R32 -> 5950 | E135: =Q32 -> 110 | F135: =DM32 -> 0 | G135: =W32 -> 360 | H135: =AQ32 -> 270 | I135: =AY32 -> 230 | J135: =DB32 -> 4540 | K135: =AN32 -> 3980 | L135: =SUM($B32:$EG32)-SUM(B135:K135) -> 64480 | O135: 2008 | P135: =D79 -> 35540 | Q135: =N79 -> 7460 | R135: =I79 -> 36510 | S135: =K79 -> 1840 | T135: =F79 -> 24210 | U135: =B79 -> 820 | V135: =L79 -> 2200 | W135: =J79 -> 390 | X135: =E79 -> 0 | Y135: =M79 -> 1550 | Z135: =SUM($B79:$O79)-SUM(P135:Y135) -> 4430
A136: 2009 | B136: =DY33 -> 23310 | C136: =G33 -> 29050 | D136: =R33 -> 7650 | E136: =Q33 -> 1010 | F136: =DM33 -> 7200 | G136: =W33 -> 3840 | H136: =AQ33 -> 270 | I136: =AY33 -> 460 | J136: =DB33 -> 6720 | K136: =AN33 -> 3980 | L136: =SUM($B33:$EG33)-SUM(B136:K136) -> 89060 | O136: 2009 | P136: =D80 -> 71210 | Q136: =N80 -> 8370 | R136: =I80 -> 46810 | S136: =K80 -> 6440 | T136: =F80 -> 27310 | U136: =B80 -> 1190 | V136: =L80 -> 3700 | W136: =J80 -> 1290 | X136: =E80 -> 0 | Y136: =M80 -> 1800 | Z136: =SUM($B80:$O80)-SUM(P136:Y136) -> 4430
A137: 2010 | B137: =DY34 -> 32130 | C137: =G34 -> 32390 | D137: =R34 -> 8780 | E137: =Q34 -> 14890 | F137: =DM34 -> 7200 | G137: =W34 -> 10920 | H137: =AQ34 -> 270 | I137: =AY34 -> 1290 | J137: =DB34 -> 6720 | K137: =AN34 -> 3980 | L137: =SUM($B34:$EG34)-SUM(B137:K137) -> 120320 | O137: 2010 | P137: =D81 -> 112400 | Q137: =N81 -> 13880 | R137: =I81 -> 55720 | S137: =K81 -> 9780 | T137: =F81 -> 30340 | U137: =B81 -> 2770 | V137: =L81 -> 4000 | W137: =J81 -> 2850 | X137: =E81 -> 100 | Y137: =M81 -> 1800 | Z137: =SUM($B81:$O81)-SUM(P137:Y137) -> 5250
A138: 2011 | B138: =DY35 -> 34300 | C138: =G35 -> 42270 | D138: =R35 -> 9290 | E138: =Q35 -> 23110 | F138: =DM35 -> 7300 | G138: =W35 -> 16380 | H138: =AQ35 -> 2310 | I138: =AY35 -> 3160 | J138: =DB35 -> 7980 | K138: =AN35 -> 7730 | L138: =SUM($B35:$EG35)-SUM(B138:K138) -> 155570 | O138: 2011 | P138: =D82 -> 150060 | Q138: =N82 -> 18620 | R138: =I82 -> 66720 | S138: =K82 -> 13500 | T138: =F82 -> 32620 | U138: =B82 -> 4380 | V138: =L82 -> 5780 | W138: =J82 -> 3820 | X138: =E82 -> 500 | Y138: =M82 -> 1800 | Z138: =SUM($B82:$O82)-SUM(P138:Y138) -> 11600
A139: 2012 | B139: =DY36 -> 43280 | C139: =G36 -> 51350 | D139: =R36 -> 16410 | E139: =Q36 -> 24860 | F139: =DM36 -> 8170 | G139: =W36 -> 37950 | H139: =AQ36 -> 5010 | I139: =AY36 -> 5260 | J139: =DB36 -> 8130 | K139: =AN36 -> 8340 | L139: =SUM($B36:$EG36)-SUM(B139:K139) -> 178160 | O139: 2012 | P139: =D83 -> 190450 | Q139: =N83 -> 21090 | R139: =I83 -> 79390 | S139: =K83 -> 18600 | T139: =F83 -> 35520 | U139: =B83 -> 8130 | V139: =L83 -> 7920 | W139: =J83 -> 5540 | X139: =E83 -> 3670 | Y139: =M83 -> 1930 | Z139: =SUM($B83:$O83)-SUM(P139:Y139) -> 14680
A140: 2013 | B140: =DY37 -> 59400 | C140: =G37 -> 60410 | D140: =R37 -> 22740 | E140: =Q37 -> 27880 | F140: =DM37 -> 8170 | G140: =W37 -> 38420 | H140: =AQ37 -> 5810 | I140: =AY37 -> 5780 | J140: =DB37 -> 9500 | K140: =AN37 -> 9230 | L140: =SUM($B37:$EG37)-SUM(B140:K140) -> 215560 | O140: 2013 | P140: =D84 -> 226210 | Q140: =N84 -> 23870 | R140: =I84 -> 85570 | S140: =K84 -> 31850 | T140: =F84 -> 36540 | U140: =B84 -> 17770 | V140: =L84 -> 8230 | W140: =J84 -> 6690 | X140: =E84 -> 4020 | Y140: =M84 -> 5460 | Z140: =SUM($B84:$O84)-SUM(P140:Y140) -> 16690
A141: 2014 | B141: =DY38 -> 77020 | C141: =G38 -> 70470 | D141: =R38 -> 29660 | E141: =Q38 -> 29460 | F141: =DM38 -> 8570 | G141: =W38 -> 42020 | H141: =AQ38 -> 7430 | I141: =AY38 -> 8370 | J141: =DB38 -> 10250 | K141: =AN38 -> 12320 | L141: =SUM($B38:$EG38)-SUM(B141:K141) -> 268070 | O141: 2014 | P141: =D85 -> 255480 | Q141: =N85 -> 30170 | R141: =I85 -> 100060 | S141: =K85 -> 47350 | T141: =F85 -> 42510 | U141: =B85 -> 25420 | V141: =L85 -> 16320 | W141: =J85 -> 8680 | X141: =E85 -> 6130 | Y141: =M85 -> 12070 | Z141: =SUM($B85:$O85)-SUM(P141:Y141) -> 19450
A142: 2015 | B142: =DY39 -> 96050 | C142: =G39 -> 81460 | D142: =R39 -> 33490 | E142: =Q39 -> 32680 | F142: =DM39 -> 12930 | G142: =W39 -> 43360 | H142: =AQ39 -> 9120 | I142: =AY39 -> 11560 | J142: =DB39 -> 14720 | K142: =AN39 -> 15310 | L142: =SUM($B39:$EG39)-SUM(B142:K142) -> 328270 | O142: 2015 | P142: =D86 -> 286880 | Q142: =N86 -> 51470 | R142: =I86 -> 105390 | S142: =K86 -> 62920 | T142: =F86 -> 56550 | U142: =B86 -> 26610 | V142: =L86 -> 25010 | W142: =J86 -> 10160 | X142: =E86 -> 9870 | Y142: =M86 -> 16070 | Z142: =SUM($B86:$O86)-SUM(P142:Y142) -> 28020
A143: 2016 | B143: =DY40 -> 151620 | C143: =G40 -> 88300 | D143: =R40 -> 44790 | E143: =Q40 -> 46090 | F143: =DM40 -> 15340 | G143: =W40 -> 46110 | H143: =AQ40 -> 21700 | I143: =AY40 -> 13980 | J143: =DB40 -> 17760 | K143: =AN40 -> 18010 | L143: =SUM($B40:$EG40)-SUM(B143:K143) -> 384380 | O143: 2016 | P143: =D87 -> 324160 | Q143: =N87 -> 62710 | R143: =I87 -> 109990 | S143: =K87 -> 79780 | T143: =F87 -> 59630 | U143: =B87 -> 32700 | V143: =L87 -> 48660 | W143: =J87 -> 22630 | X143: =E87 -> 31900 | Y143: =M87 -> 38440 | Z143: =SUM($B87:$O87)-SUM(P143:Y143) -> 37480
... A152: 2025 | B152: =DY49 -> 204880 | C152: =G49 -> 108180 | D152: =R49 -> 107050 | E152: =Q49 -> 80550 | F152: =DM49 -> 62870 | G152: =W49 -> 57280 | H152: =AQ49 -> 56340 | I152: =AY49 -> 49350 | J152: =DB49 -> 46830 | K152: =AN49 -> 37130 | L152: =SUM($B49:$EG49)-SUM(B152:K152) -> 760970 | O152: 2025 | P152: =D96 -> 485700 | Q152: =N96 -> 203400 | R152: =I96 -> 202780 | S152: =K96 -> 120440 | T152: =F96 -> 89640 | U152: =B96 -> 88120 | V152: =L96 -> 84460 | W152: =J96 -> 78310 | X152: =E96 -> 65600 | Y152: =M96 -> 48140 | Z152: =SUM($B96:$O96)-SUM(P152:Y152) -> 104840
